Workbook

Sheet MasterData
A1: ⚙ MASTER DATA — Add new entries at the bottom of any column.
A2: 💡 To add a new client: add next ID (CLI-XXX) in col A and name in col B. All other lists: just add below the last entry.
A3: Client ID | B3: Client Name | C3: Roles | D3: Departments | E3: Cities | F3: Seniority | G3: Pipeline Stages | H3: Position Status | I3: Recruiters
A4: CLI-001 | B4: ABNAH | C4: ARM | D4: F&B - Kitchen | E4: Mumbai | F4: Trainee | G4: Sent to Client | H4: Open | I4: Edwin
A5: CLI-002 | B5: Abhinav Immigration | C5: Assistant Bartender | D5: F&B - Service | E5: Delhi | F5: Junior | G5: Interview Scheduled | H5: On Hold | I5: Manokamna
A6: CLI-003 | B6: Adarsh Sweets | C6: Assistant Front Office Manager | D6: Bar & Beverages | E6: Bangalore | F6: Mid | G6: Result Awaited | H6: Closed - Filled | I6: Hardik
A7: CLI-004 | B7: Agarwal Biryani | C7: Assistant Manager | D7: Front Office & Rooms | E7: Hyderabad | F7: Senior | G7: Selected | H7: Closed - Cancelled | I7: Mohit
A8: CLI-005 | B8: All in | C8: Assistant Outlet Manager | D8: Housekeeping | E8: Pune | F8: Leadership | G8: Rejected | I8: Aakash
A9: CLI-006 | B9: Aria Communication | C9: Assistant Stores Manager | D9: HR & Training | E9: Goa | G9: Hold
A10: CLI-007 | B10: Atmosphere | C10: Asst Cafe Manager | D10: Marketing & PR | E10: Chennai | G10: Offer Sent
A11: CLI-008 | B11: August Café | C11: Bar Lead | D11: Sales & Revenue | E11: Kolkata | G11: Offer Accepted
A12: CLI-009 | B12: Aures hospitality | C12: Bar Manager | D12: Finance & Accounts | E12: Ahmedabad | G12: Joined
A13: CLI-010 | B13: BB | C13: Bar Supervisor | D13: Operations | E13: Jaipur | G13: Candidate Dropped
A14: CLI-011 | B14: BTC | C14: Barback | D14: Store & Purchase | E14: Other
A15: CLI-012 | B15: Baesic Fit | C15: Barista | D15: Tech & Data
A16: CLI-013 | B16: Bare | C16: Barista Head | D16: Other
A17: CLI-014 | B17: Blondie | C17: Barista Trainer
A18: CLI-015 | B18: Circa 11 | C18: Bartender
A19: CLI-016 | B19: CocoCart | C19: CDP
A20: CLI-017 | B20: DU Hospitality | C20: CRM
A21: CLI-018 | B21: Diva | C21: Cafe Manager
A22: CLI-019 | B22: Donmai | C22: Cafe Supervisor
A23: CLI-020 | B23: Doppler | C23: Captain
A24: CLI-021 | B24: Dough and Joe | C24: Cashier
A25: CLI-022 | B25: EDD | C25: Chef
A26: CLI-023 | B26: FHPL | C26: Commi
A27: CLI-024 | B27: Flavour Pots | C27: Commi 1
A28: CLI-025 | B28: Food Square | C28: Commi 2
... A81: CLI-078 | B81: Niko | C81: Senior Barista
B82: Courtside | C82: Senior Bartender
B83: Penang Table | C83: Senior CDP
B84: TGC | C84: Senior Captain
B85: Corleone's | C85: Senior GRE
B86: Nenapu | C86: Senior Sous Chef
C87: Senior Steward
C88: Social Media Manager
C89: Sommelier
C90: Sous Chef
C91: Sr. Duty Manager
C92: Steward
C93: Store Manager
C94: Stores Manager
C95: Supervisor
C96: Supply Chain
C97: Team Leader
C98: Trainee Captain
... C103: Barista

Sheet Open Positions
A1: 🏨 OPEN POSITIONS
A2: 💡 Select Client Name → Position ID, Client ID, Filled and Remaining populate automatically. Teal columns are auto — do not edit.
A3: Position ID | B3: Client Name | C3: Role | D3: Department | E3: City | F3: Seniority | G3: Date Opened | H3: Target Close | I3: Assigned To | J3: No. of Openings | K3: Status | L3: Remarks | M3: Client ID | N3: Filled | O3: Remaining
A4: CLI-031-POS-001 | B4: Hunger Inc | C4: Cafe Steward | D4: F&B - Service | E4: Mumbai | F4: Junior | I4: Edwin | J4: 7 | K4: Open | M4: CLI-031 | N4: 3 | O4: =IF(J4="","",J4-N4) -> 4 | Q4: =IFERROR(MasterData!$B4,"") -> ABNAH | R4: =IFERROR(MasterData!$C4,"") -> ARM | S4: =IFERROR(MasterData!$D4,"") -> F&B - Kitchen | T4: =IFERROR(MasterData!$E4,"") -> Mumbai | U4: =IFERROR(MasterData!$F4,"") -> Trainee | V4: =IFERROR(MasterData!$I4,"") -> Edwin | W4: =IFERROR(MasterData!$H4,"") -> Open
A5: CLI-031-POS-002 | B5: Hunger Inc | C5: Captain | D5: F&B - Service | E5: Mumbai | F5: Junior | I5: Edwin | J5: 7 | K5: Open | M5: CLI-031 | N5: 0 | O5: =IF(J5="","",J5-N5) -> 7 | Q5: =IFERROR(MasterData!$B5,"") -> Abhinav Immigration | R5: =IFERROR(MasterData!$C5,"") -> Assistant Bartender | S5: =IFERROR(MasterData!$D5,"") -> F&B - Service | T5: =IFERROR(MasterData!$E5,"") -> Delhi | U5: =IFERROR(MasterData!$F5,"") -> Junior | V5: =IFERROR(MasterData!$I5,"") -> Manokamna | W5: =IFERROR(MasterData!$H5,"") -> On Hold
A6: CLI-026-POS-001 | B6: Foodmatters | C6: Captain | D6: F&B - Service | E6: Mumbai | F6: Junior | I6: Edwin | J6: 0 | K6: Closed | M6: CLI-026 | N6: 0 | O6: =IF(J6="","",J6-N6) -> 0 | Q6: =IFERROR(MasterData!$B6,"") -> Adarsh Sweets | R6: =IFERROR(MasterData!$C6,"") -> Assistant Front Office Manager | S6: =IFERROR(MasterData!$D6,"") -> Bar & Beverages | T6: =IFERROR(MasterData!$E6,"") -> Bangalore | U6: =IFERROR(MasterData!$F6,"") -> Mid | V6: =IFERROR(MasterData!$I6,"") -> Hardik | W6: =IFERROR(MasterData!$H6,"") -> Closed - Filled
A7: CLI-026-POS-002 | B7: Foodmatters | C7: Steward | D7: F&B - Service | E7: Mumbai | F7: Junior | I7: Edwin | J7: 8 | K7: Open | M7: CLI-026 | N7: 0 | O7: =IF(J7="","",J7-N7) -> 8 | Q7: =IFERROR(MasterData!$B7,"") -> Agarwal Biryani | R7: =IFERROR(MasterData!$C7,"") -> Assistant Manager | S7: =IFERROR(MasterData!$D7,"") -> Front Office & Rooms | T7: =IFERROR(MasterData!$E7,"") -> Hyderabad | U7: =IFERROR(MasterData!$F7,"") -> Senior | V7: =IFERROR(MasterData!$I7,"") -> Mohit | W7: =IFERROR(MasterData!$H7,"") -> Closed - Cancelled
A8: CLI-026-POS-003 | B8: Foodmatters | C8: Bartender | D8: F&B - Service | E8: Mumbai | F8: Junior | I8: Edwin | J8: 0 | K8: Closed | M8: CLI-026 | N8: 0 | O8: =IF(J8="","",J8-N8) -> 0 | Q8: =IFERROR(MasterData!$B8,"") -> All in | R8: =IFERROR(MasterData!$C8,"") -> Assistant Outlet Manager | S8: =IFERROR(MasterData!$D8,"") -> Housekeeping | T8: =IFERROR(MasterData!$E8,"") -> Pune | U8: =IFERROR(MasterData!$F8,"") -> Leadership | V8: =IFERROR(MasterData!$I8,"") -> Aakash | W8: =IFERROR(MasterData!$H8,"")
A9: CLI-001-POS-001 | B9: ABNAH | C9: Steward | D9: F&B - Service | E9: Mumbai | F9: Junior | I9: Mohit | J9: 5 | K9: Open | M9: CLI-001 | N9: 0 | O9: =IF(J9="","",J9-N9) -> 5 | Q9: =IFERROR(MasterData!$B9,"") -> Aria Communication | R9: =IFERROR(MasterData!$C9,"") -> Assistant Stores Manager | S9: =IFERROR(MasterData!$D9,"") -> HR & Training | T9: =IFERROR(MasterData!$E9,"") -> Goa | U9: =IFERROR(MasterData!$F9,"") | V9: =IFERROR(MasterData!$I9,"") | W9: =IFERROR(MasterData!$H9,"")
A10: CLI-001-POS-002 | B10: ABNAH | C10: GRE | D10: F&B - Service | E10: Mumbai | F10: Junior | I10: Mohit | J10: 3 | K10: Open | M10: CLI-001 | N10: 0 | O10: =IF(J10="","",J10-N10) -> 3 | Q10: =IFERROR(MasterData!$B10,"") -> Atmosphere | R10: =IFERROR(MasterData!$C10,"") -> Asst Cafe Manager | S10: =IFERROR(MasterData!$D10,"") -> Marketing & PR | T10: =IFERROR(MasterData!$E10,"") -> Chennai | U10: =IFERROR(MasterData!$F10,"") | V10: =IFERROR(MasterData!$I10,"") | W10: =IFERROR(MasterData!$H10,"")
A11: CLI-001-POS-003 | B11: ABNAH | C11: Bartender | D11: F&B - Service | E11: Mumbai | F11: Junior | I11: Mohit | J11: 3 | K11: Open | M11: CLI-001 | N11: 0 | O11: =IF(J11="","",J11-N11) -> 3 | Q11: =IFERROR(MasterData!$B11,"") -> August Café | R11: =IFERROR(MasterData!$C11,"") -> Bar Lead | S11: =IFERROR(MasterData!$D11,"") -> Sales & Revenue | T11: =IFERROR(MasterData!$E11,"") -> Kolkata | U11: =IFERROR(MasterData!$F11,"") | V11: =IFERROR(MasterData!$I11,"") | W11: =IFERROR(MasterData!$H11,"")
A12: CLI-014-POS-001 | B12: Blondie | C12: ARM | D12: F&B - Service | E12: Mumbai | F12: Mid | I12: Aakash | J12: 3 | K12: Open | M12: CLI-014 | N12: 0 | O12: =IF(J12="","",J12-N12) -> 3 | Q12: =IFERROR(MasterData!$B12,"") -> Aures hospitality | R12: =IFERROR(MasterData!$C12,"") -> Bar Manager | S12: =IFERROR(MasterData!$D12,"") -> Finance & Accounts | T12: =IFERROR(MasterData!$E12,"") -> Ahmedabad | U12: =IFERROR(MasterData!$F12,"") | V12: =IFERROR(MasterData!$I12,"") | W12: =IFERROR(MasterData!$H12,"")
A13: CLI-014-POS-002 | B13: Blondie | C13: RM | D13: F&B - Service | E13: Mumbai | F13: Mid | I13: Aakash | J13: 3 | K13: Open | M13: CLI-014 | N13: 0 | O13: =IF(J13="","",J13-N13) -> 3 | Q13: =IFERROR(MasterData!$B13,"") -> BB | R13: =IFERROR(MasterData!$C13,"") -> Bar Supervisor | S13: =IFERROR(MasterData!$D13,"") -> Operations | T13: =IFERROR(MasterData!$E13,"") -> Jaipur | U13: =IFERROR(MasterData!$F13,"") | V13: =IFERROR(MasterData!$I13,"") | W13: =IFERROR(MasterData!$H13,"")
A14: CLI-014-POS-003 | B14: Blondie | C14: Operations Head | D14: Operations | E14: Mumbai | F14: Senior | I14: Aakash | J14: 1 | K14: Closed | M14: CLI-014 | N14: 0 | O14: =IF(J14="","",J14-N14) -> 1 | Q14: =IFERROR(MasterData!$B14,"") -> BTC | R14: =IFERROR(MasterData!$C14,"") -> Barback | S14: =IFERROR(MasterData!$D14,"") -> Store & Purchase | T14: =IFERROR(MasterData!$E14,"") -> Other | U14: =IFERROR(MasterData!$F14,"") | V14: =IFERROR(MasterData!$I14,"") | W14: =IFERROR(MasterData!$H14,"")
A15: CLI-014-POS-004 | B15: Blondie | C15: Social Media Manager | D15: Marketing & PR | E15: Mumbai | F15: Junior | I15: Aakash | J15: 2 | K15: Open | M15: CLI-014 | N15: 2 | O15: =IF(J15="","",J15-N15) -> 0 | Q15: =IFERROR(MasterData!$B15,"") -> Baesic Fit | R15: =IFERROR(MasterData!$C15,"") -> Barista | S15: =IFERROR(MasterData!$D15,"") -> Tech & Data | T15: =IFERROR(MasterData!$E15,"") | U15: =IFERROR(MasterData!$F15,"") | V15: =IFERROR(MasterData!$I15,"") | W15: =IFERROR(MasterData!$H15,"")
A16: CLI-016-POS-001 | B16: CocoCart | C16: F&B Associate | D16: F&B - Service | E16: Mumbai | F16: Junior | I16: Mohit | J16: 35 | K16: Open | M16: CLI-016 | N16: 0 | O16: =IF(J16="","",J16-N16) -> 35 | Q16: =IFERROR(MasterData!$B16,"") -> Bare | R16: =IFERROR(MasterData!$C16,"") -> Barista Head | S16: =IFERROR(MasterData!$D16,"") -> Other | T16: =IFERROR(MasterData!$E16,"") | U16: =IFERROR(MasterData!$F16,"") | V16: =IFERROR(MasterData!$I16,"") | W16: =IFERROR(MasterData!$H16,"")
A17: CLI-071-POS-001 | B17: UGIPL | C17: Sous Chef | D17: F&B - Kitchen | E17: Mumbai | F17: Senior | I17: Mohit | J17: 1 | K17: Open | L17: Pizza Chef | M17: CLI-071 | N17: 0 | O17: =IF(J17="","",J17-N17) -> 1 | Q17: =IFERROR(MasterData!$B17,"") -> Blondie | R17: =IFERROR(MasterData!$C17,"") -> Barista Trainer | S17: =IFERROR(MasterData!$D17,"") | T17: =IFERROR(MasterData!$E17,"") | U17: =IFERROR(MasterData!$F17,"") | V17: =IFERROR(MasterData!$I17,"") | W17: =IFERROR(MasterData!$H17,"")
A18: CLI-071-POS-002 | B18: UGIPL | C18: Outlet Supervisor | D18: F&B - Service | E18: Mumbai | F18: Mid | I18: Manokamna | J18: 3 | K18: Open | M18: CLI-071 | N18: 0 | O18: =IF(J18="","",J18-N18) -> 3 | Q18: =IFERROR(MasterData!$B18,"") -> Circa 11 | R18: =IFERROR(MasterData!$C18,"") -> Bartender | S18: =IFERROR(MasterData!$D18,"") | T18: =IFERROR(MasterData!$E18,"") | U18: =IFERROR(MasterData!$F18,"") | V18: =IFERROR(MasterData!$I18,"") | W18: =IFERROR(MasterData!$H18,"")
A19: CLI-071-POS-003 | B19: UGIPL | C19: Steward | D19: F&B - Service | E19: Mumbai | F19: Junior | I19: Manokamna | J19: 8 | K19: Open | M19: CLI-071 | N19: 0 | O19: =IF(J19="","",J19-N19) -> 8 | Q19: =IFERROR(MasterData!$B19,"") -> CocoCart | R19: =IFERROR(MasterData!$C19,"") -> CDP | S19: =IFERROR(MasterData!$D19,"") | T19: =IFERROR(MasterData!$E19,"") | U19: =IFERROR(MasterData!$F19,"") | V19: =IFERROR(MasterData!$I19,"") | W19: =IFERROR(MasterData!$H19,"")
A20: CLI-061-POS-001 | B20: Speciality | C20: RM | D20: F&B - Service | E20: Delhi | F20: Mid | I20: Hardik | J20: 2 | K20: Open | M20: CLI-061 | N20: 0 | O20: =IF(J20="","",J20-N20) -> 2 | Q20: =IFERROR(MasterData!$B20,"") -> DU Hospitality | R20: =IFERROR(MasterData!$C20,"") -> CRM | S20: =IFERROR(MasterData!$D20,"") | T20: =IFERROR(MasterData!$E20,"") | U20: =IFERROR(MasterData!$F20,"") | V20: =IFERROR(MasterData!$I20,"") | W20: =IFERROR(MasterData!$H20,"")
A21: CLI-061-POS-002 | B21: Speciality | C21: ARM | D21: F&B - Service | E21: Delhi | F21: Mid | I21: Hardik | J21: 2 | K21: Open | M21: CLI-061 | N21: 0 | O21: =IF(J21="","",J21-N21) -> 2 | Q21: =IFERROR(MasterData!$B21,"") -> Diva | R21: =IFERROR(MasterData!$C21,"") -> Cafe Manager | S21: =IFERROR(MasterData!$D21,"") | T21: =IFERROR(MasterData!$E21,"") | U21: =IFERROR(MasterData!$F21,"") | V21: =IFERROR(MasterData!$I21,"") | W21: =IFERROR(MasterData!$H21,"")
A22: CLI-061-POS-003 | B22: Speciality | C22: ARM | D22: F&B - Service | E22: Pune | F22: Mid | I22: Hardik | J22: 2 | K22: Open | M22: CLI-061 | N22: 0 | O22: =IF(J22="","",J22-N22) -> 2 | Q22: =IFERROR(MasterData!$B22,"") -> Donmai | R22: =IFERROR(MasterData!$C22,"") -> Cafe Supervisor | S22: =IFERROR(MasterData!$D22,"") | T22: =IFERROR(MasterData!$E22,"") | U22: =IFERROR(MasterData!$F22,"") | V22: =IFERROR(MasterData!$I22,"") | W22: =IFERROR(MasterData!$H22,"")
A23: CLI-061-POS-004 | B23: Speciality | C23: Executive Chef | D23: F&B - Kitchen | E23: Delhi | F23: Leadership | G23: 46085 | H23: 46104 | I23: Hardik | J23: 2 | K23: Closed | L23: Selected and Joining from 1st of May | M23: CLI-061 | N23: 1 | O23: =IF(J23="","",J23-N23) -> 1 | Q23: =IFERROR(MasterData!$B23,"") -> Doppler | R23: =IFERROR(MasterData!$C23,"") -> Captain | S23: =IFERROR(MasterData!$D23,"") | T23: =IFERROR(MasterData!$E23,"") | U23: =IFERROR(MasterData!$F23,"") | V23: =IFERROR(MasterData!$I23,"") | W23: =IFERROR(MasterData!$H23,"")
A24: CLI-061-POS-005 | B24: Speciality | C24: Executive Chef | D24: F&B - Kitchen | E24: Pune | F24: Leadership | I24: Hardik | J24: 1 | K24: Open | M24: CLI-061 | N24: 0 | O24: =IF(J24="","",J24-N24) -> 1 | Q24: =IFERROR(MasterData!$B24,"") -> Dough and Joe | R24: =IFERROR(MasterData!$C24,"") -> Cashier | S24: =IFERROR(MasterData!$D24,"") | T24: =IFERROR(MasterData!$E24,"") | U24: =IFERROR(MasterData!$F24,"") | V24: =IFERROR(MasterData!$I24,"") | W24: =IFERROR(MasterData!$H24,"")
A25: CLI-061-POS-006 | B25: Speciality | C25: Marketing Head | D25: Marketing & PR | E25: Delhi | F25: Leadership | G25: 46086 | H25: 46089 | I25: Hardik | J25: 1 | K25: Closed | M25: CLI-061 | N25: 1 | O25: =IF(J25="","",J25-N25) -> 0 | Q25: =IFERROR(MasterData!$B25,"") -> EDD | R25: =IFERROR(MasterData!$C25,"") -> Chef | S25: =IFERROR(MasterData!$D25,"") | T25: =IFERROR(MasterData!$E25,"") | U25: =IFERROR(MasterData!$F25,"") | V25: =IFERROR(MasterData!$I25,"") | W25: =IFERROR(MasterData!$H25,"")
A26: CLI-045-POS-001 | B26: Neighbourhood | C26: Community Manager | D26: Marketing & PR | E26: Bangalore | F26: Mid | I26: Hardik | J26: 1 | K26: Open | M26: CLI-045 | N26: 0 | O26: =IF(J26="","",J26-N26) -> 1 | Q26: =IFERROR(MasterData!$B26,"") -> FHPL | R26: =IFERROR(MasterData!$C26,"") -> Commi | S26: =IFERROR(MasterData!$D26,"") | T26: =IFERROR(MasterData!$E26,"") | U26: =IFERROR(MasterData!$F26,"") | V26: =IFERROR(MasterData!$I26,"") | W26: =IFERROR(MasterData!$H26,"")
A27: CLI-045-POS-002 | B27: Neighbourhood | C27: Community Manager | D27: Marketing & PR | E27: Mumbai | F27: Mid | I27: Hardik | J27: 1 | K27: Open | M27: CLI-045 | N27: 0 | O27: =IF(J27="","",J27-N27) -> 1 | Q27: =IFERROR(MasterData!$B27,"") -> Flavour Pots | R27: =IFERROR(MasterData!$C27,"") -> Commi 1 | S27: =IFERROR(MasterData!$D27,"") | T27: =IFERROR(MasterData!$E27,"") | U27: =IFERROR(MasterData!$F27,"") | V27: =IFERROR(MasterData!$I27,"") | W27: =IFERROR(MasterData!$H27,"")
A28: CLI-022-POS-001 | B28: EDD | C28: HR Head | D28: HR & Training | E28: Mumbai | F28: Senior | I28: Aakash | J28: 1 | K28: Open | M28: CLI-022 | N28: 0 | O28: =IF(J28="","",J28-N28) -> 1 | Q28: =IFERROR(MasterData!$B28,"") -> Food Square | R28: =IFERROR(MasterData!$C28,"") -> Commi 2 | S28: =IFERROR(MasterData!$D28,"") | T28: =IFERROR(MasterData!$E28,"") | U28: =IFERROR(MasterData!$F28,"") | V28: =IFERROR(MasterData!$I28,"") | W28: =IFERROR(MasterData!$H28,"")
A29: CLI-022-POS-002 | B29: EDD | C29: Sous Chef | D29: F&B - Kitchen | E29: Mumbai | F29: Senior | I29: Aakash | J29: 1 | K29: Open | M29: CLI-022 | N29: 0 | O29: =IF(J29="","",J29-N29) -> 1 | Q29: =IFERROR(MasterData!$B29,"") -> Foodmatters | R29: =IFERROR(MasterData!$C29,"") -> Commi 3 | S29: =IFERROR(MasterData!$D29,"") | T29: =IFERROR(MasterData!$E29,"") | U29: =IFERROR(MasterData!$F29,"") | V29: =IFERROR(MasterData!$I29,"") | W29: =IFERROR(MasterData!$H29,"")
A30: CLI-022-POS-003 | B30: EDD | C30: CDP | D30: F&B - Kitchen | E30: Mumbai | F30: Mid | I30: Aakash | J30: 1 | K30: Open | M30: CLI-022 | N30: 0 | O30: =IF(J30="","",J30-N30) -> 1 | Q30: =IFERROR(MasterData!$B30,"") -> Ghostkitchens | R30: =IFERROR(MasterData!$C30,"") -> Community Manager | S30: =IFERROR(MasterData!$D30,"") | T30: =IFERROR(MasterData!$E30,"") | U30: =IFERROR(MasterData!$F30,"") | V30: =IFERROR(MasterData!$I30,"") | W30: =IFERROR(MasterData!$H30,"")
A31: CLI-022-POS-004 | B31: EDD | C31: Commi | D31: F&B - Kitchen | E31: Mumbai | F31: Junior | I31: Aakash | J31: 5 | K31: Open | M31: CLI-022 | N31: 0 | O31: =IF(J31="","",J31-N31) -> 5 | Q31: =IFERROR(MasterData!$B31,"") -> Gupta Brands | R31: =IFERROR(MasterData!$C31,"") -> Content Strategist | S31: =IFERROR(MasterData!$D31,"") | T31: =IFERROR(MasterData!$E31,"") | U31: =IFERROR(MasterData!$F31,"") | V31: =IFERROR(MasterData!$I31,"") | W31: =IFERROR(MasterData!$H31,"")
A32: CLI-022-POS-005 | B32: EDD | C32: Captain | D32: F&B - Service | E32: Mumbai | F32: Junior | I32: Aakash | J32: 5 | K32: Open | M32: CLI-022 | N32: 0 | O32: =IF(J32="","",J32-N32) -> 5 | Q32: =IFERROR(MasterData!$B32,"") -> Huddle and Score | R32: =IFERROR(MasterData!$C32,"") -> Counter Sales | S32: =IFERROR(MasterData!$D32,"") | T32: =IFERROR(MasterData!$E32,"") | U32: =IFERROR(MasterData!$F32,"") | V32: =IFERROR(MasterData!$I32,"") | W32: =IFERROR(MasterData!$H32,"")
A33: CLI-038-POS-001 | B33: La Loca Maria | C33: Chef | D33: F&B - Kitchen | E33: Mumbai | F33: Leadership | I33: Edwin | J33: 0 | K33: Open | L33: Chef De Cuisine | M33: CLI-038 | N33: 0 | O33: =IF(J33="","",J33-N33) -> 0 | Q33: =IFERROR(MasterData!$B33,"") -> Hummingtree | R33: =IFERROR(MasterData!$C33,"") -> DCDP | S33: =IFERROR(MasterData!$D33,"") | T33: =IFERROR(MasterData!$E33,"") | U33: =IFERROR(MasterData!$F33,"") | V33: =IFERROR(MasterData!$I33,"") | W33: =IFERROR(MasterData!$H33,"")
A34: CLI-038-POS-002 | B34: La Loca Maria | C34: Sous Chef | D34: F&B - Kitchen | E34: Mumbai | F34: Senior | I34: Edwin | J34: 1 | K34: Open | M34: CLI-038 | N34: 0 | O34: =IF(J34="","",J34-N34) -> 1 | Q34: =IFERROR(MasterData!$B34,"") -> Hunger Inc | R34: =IFERROR(MasterData!$C34,"") -> Data Analyst | S34: =IFERROR(MasterData!$D34,"") | T34: =IFERROR(MasterData!$E34,"") | U34: =IFERROR(MasterData!$F34,"") | V34: =IFERROR(MasterData!$I34,"") | W34: =IFERROR(MasterData!$H34,"")
A35: CLI-038-POS-003 | B35: La Loca Maria | C35: Mixologist | D35: Bar & Beverages | E35: Mumbai | F35: Senior | I35: Edwin | J35: 1 | K35: Open | M35: CLI-038 | N35: 0 | O35: =IF(J35="","",J35-N35) -> 1 | Q35: =IFERROR(MasterData!$B35,"") -> Idoru | R35: =IFERROR(MasterData!$C35,"") -> Director of Operations | S35: =IFERROR(MasterData!$D35,"") | T35: =IFERROR(MasterData!$E35,"") | U35: =IFERROR(MasterData!$F35,"") | V35: =IFERROR(MasterData!$I35,"") | W35: =IFERROR(MasterData!$H35,"")
A36: CLI-038-POS-004 | B36: La Loca Maria | C36: Captain | D36: F&B - Service | E36: Mumbai | F36: Junior | I36: Edwin | J36: 10 | K36: Open | M36: CLI-038 | N36: 0 | O36: =IF(J36="","",J36-N36) -> 10 | Q36: =IFERROR(MasterData!$B36,"") -> Ikai | R36: =IFERROR(MasterData!$C36,"") -> Duty Manager | S36: =IFERROR(MasterData!$D36,"") | T36: =IFERROR(MasterData!$E36,"") | U36: =IFERROR(MasterData!$F36,"") | V36: =IFERROR(MasterData!$I36,"") | W36: =IFERROR(MasterData!$H36,"")
A37: CLI-038-POS-005 | B37: La Loca Maria | C37: Bartender | D37: Bar & Beverages | E37: Mumbai | F37: Junior | I37: Edwin | J37: 5 | K37: Open | M37: CLI-038 | N37: 0 | O37: =IF(J37="","",J37-N37) -> 5 | Q37: =IFERROR(MasterData!$B37,"") -> Izumi | R37: =IFERROR(MasterData!$C37,"") -> EA | S37: =IFERROR(MasterData!$D37,"") | T37: =IFERROR(MasterData!$E37,"") | U37: =IFERROR(MasterData!$F37,"") | V37: =IFERROR(MasterData!$I37,"") | W37: =IFERROR(MasterData!$H37,"")
A38: CLI-038-POS-006 | B38: La Loca Maria | C38: Commi | D38: F&B - Kitchen | E38: Mumbai | F38: Junior | I38: Edwin | J38: 10 | K38: Open | M38: CLI-038 | N38: 0 | O38: =IF(J38="","",J38-N38) -> 10 | Q38: =IFERROR(MasterData!$B38,"") -> Izumi - GOA | R38: =IFERROR(MasterData!$C38,"") -> Executive Chef | S38: =IFERROR(MasterData!$D38,"") | T38: =IFERROR(MasterData!$E38,"") | U38: =IFERROR(MasterData!$F38,"") | V38: =IFERROR(MasterData!$I38,"") | W38: =IFERROR(MasterData!$H38,"")
A39: CLI-015-POS-001 | B39: Circa 11 | C39: CDP | D39: F&B - Kitchen | E39: Bangalore | F39: Mid | I39: Edwin | J39: 1 | K39: Open | M39: CLI-015 | N39: 0 | O39: =IF(J39="","",J39-N39) -> 1 | Q39: =IFERROR(MasterData!$B39,"") -> Kaia | R39: =IFERROR(MasterData!$C39,"") -> F&B Associate | S39: =IFERROR(MasterData!$D39,"") | T39: =IFERROR(MasterData!$E39,"") | U39: =IFERROR(MasterData!$F39,"") | V39: =IFERROR(MasterData!$I39,"") | W39: =IFERROR(MasterData!$H39,"")
A40: CLI-015-POS-002 | B40: Circa 11 | C40: Bartender | D40: Bar & Beverages | E40: Bangalore | F40: Junior | I40: Edwin | J40: 1 | K40: Open | M40: CLI-015 | N40: 0 | O40: =IF(J40="","",J40-N40) -> 1 | Q40: =IFERROR(MasterData!$B40,"") -> Kohinoor Group | R40: =IFERROR(MasterData!$C40,"") -> F&B Controller | S40: =IFERROR(MasterData!$D40,"") | T40: =IFERROR(MasterData!$E40,"") | U40: =IFERROR(MasterData!$F40,"") | V40: =IFERROR(MasterData!$I40,"") | W40: =IFERROR(MasterData!$H40,"")
A41: CLI-005-POS-001 | B41: All in | C41: Banquet Manager | D41: Front Office & Rooms | E41: Mumbai | F41: Mid | I41: Manokamna | J41: 1 | K41: Open | M41: CLI-005 | N41: 0 | O41: =IF(J41="","",J41-N41) -> 1 | Q41: =IFERROR(MasterData!$B41,"") -> La Loca Maria | R41: =IFERROR(MasterData!$C41,"") -> F&B Executive | S41: =IFERROR(MasterData!$D41,"") | T41: =IFERROR(MasterData!$E41,"") | U41: =IFERROR(MasterData!$F41,"") | V41: =IFERROR(MasterData!$I41,"") | W41: =IFERROR(MasterData!$H41,"")
A42: CLI-005-POS-002 | B42: All in | C42: Captain | D42: F&B - Kitchen | E42: Mumbai | F42: Junior | I42: Manokamna | J42: 7 | K42: Open | M42: CLI-005 | N42: 0 | O42: =IF(J42="","",J42-N42) -> 7 | Q42: =IFERROR(MasterData!$B42,"") -> Le 15 | R42: =IFERROR(MasterData!$C42,"") -> F&B Supervisor | S42: =IFERROR(MasterData!$D42,"") | T42: =IFERROR(MasterData!$E42,"") | U42: =IFERROR(MasterData!$F42,"") | V42: =IFERROR(MasterData!$I42,"") | W42: =IFERROR(MasterData!$H42,"")
A43: CLI-005-POS-003 | B43: All in | C43: Bartender | D43: Bar & Beverages | E43: Mumbai | F43: Junior | I43: Manokamna | J43: 3 | K43: Open | M43: CLI-005 | N43: 0 | O43: =IF(J43="","",J43-N43) -> 3 | Q43: =IFERROR(MasterData!$B43,"") -> Malsons | R43: =IFERROR(MasterData!$C43,"") -> FOE | S43: =IFERROR(MasterData!$D43,"") | T43: =IFERROR(MasterData!$E43,"") | U43: =IFERROR(MasterData!$F43,"") | V43: =IFERROR(MasterData!$I43,"") | W43: =IFERROR(MasterData!$H43,"")
A44: CLI-073-POS-001 | B44: HNH Salad | C44: Chef | D44: F&B - Kitchen | E44: Mumbai | F44: Mid | G44: 46097 | I44: Aakash | J44: 1 | K44: Open | L44: R&D Chef | M44: CLI-073 | N44: 0 | O44: =IF(J44="","",J44-N44) -> 1 | Q44: =IFERROR(MasterData!$B44,"") -> Mia Cucina | R44: =IFERROR(MasterData!$C44,"") -> Floor Supervisor | S44: =IFERROR(MasterData!$D44,"") | T44: =IFERROR(MasterData!$E44,"") | U44: =IFERROR(MasterData!$F44,"") | V44: =IFERROR(MasterData!$I44,"") | W44: =IFERROR(MasterData!$H44,"")
A45: CLI-073-POS-002 | B45: HNH Salad | C45: Purchase | D45: Store & Purchase | E45: Mumbai | F45: Mid | G45: 46097 | I45: Aakash | J45: 1 | K45: Open | M45: CLI-073 | N45: 0 | O45: =IF(J45="","",J45-N45) -> 1 | Q45: =IFERROR(MasterData!$B45,"") -> Milagro (SLH) | R45: =IFERROR(MasterData!$C45,"") -> Front Desk | S45: =IFERROR(MasterData!$D45,"") | T45: =IFERROR(MasterData!$E45,"") | U45: =IFERROR(MasterData!$F45,"") | V45: =IFERROR(MasterData!$I45,"") | W45: =IFERROR(MasterData!$H45,"")
A46: CLI-073-POS-003 | B46: HNH Salad | C46: F&B Associate | D46: F&B - Service | E46: Mumbai | F46: Junior | G46: 46097 | I46: Aakash | J46: 30 | K46: Open | M46: CLI-073 | N46: 0 | O46: =IF(J46="","",J46-N46) -> 30 | Q46: =IFERROR(MasterData!$B46,"") -> Monarch | R46: =IFERROR(MasterData!$C46,"") -> GRE | S46: =IFERROR(MasterData!$D46,"") | T46: =IFERROR(MasterData!$E46,"") | U46: =IFERROR(MasterData!$F46,"") | V46: =IFERROR(MasterData!$I46,"") | W46: =IFERROR(MasterData!$H46,"")
A47: CLI-074-POS-001 | B47: Apero by Malvika | C47: Commi | D47: F&B - Kitchen | E47: Mumbai | F47: Junior | G47: 46098 | I47: Manokamna | J47: 2 | K47: Open | L47: Cold and hot kitchen | M47: CLI-074 | N47: 0 | O47: =IF(J47="","",J47-N47) -> 2 | Q47: =IFERROR(MasterData!$B47,"") -> NOTO | R47: =IFERROR(MasterData!$C47,"") -> GRM | S47: =IFERROR(MasterData!$D47,"") | T47: =IFERROR(MasterData!$E47,"") | U47: =IFERROR(MasterData!$F47,"") | V47: =IFERROR(MasterData!$I47,"") | W47: =IFERROR(MasterData!$H47,"")
A48: CLI-075-POS-001 | B48: Bastian | C48: Social Media Manager | D48: Marketing & PR | E48: Mumbai | F48: Junior | G48: 46082 | I48: Aakash | J48: 2 | K48: Closed - Filled | M48: CLI-075 | N48: 0 | O48: =IF(J48="","",J48-N48) -> 2 | Q48: =IFERROR(MasterData!$B48,"") -> Neighbourhood | R48: =IFERROR(MasterData!$C48,"") -> General Manager | S48: =IFERROR(MasterData!$D48,"") | T48: =IFERROR(MasterData!$E48,"") | U48: =IFERROR(MasterData!$F48,"") | V48: =IFERROR(MasterData!$I48,"") | W48: =IFERROR(MasterData!$H48,"")
A49: CLI-075-POS-002 | B49: Bastian | C49: Operations Manager | D49: F&B - Service | E49: Mumbai | F49: Mid | G49: 46091 | I49: Hardik | J49: 1 | K49: Open | L49: Cloud Kitchen | M49: CLI-075 | N49: 0 | O49: =IF(J49="","",J49-N49) -> 1 | Q49: =IFERROR(MasterData!$B49,"") -> Nidhi and Mihir PR | R49: =IFERROR(MasterData!$C49,"") -> HK Supervisor | S49: =IFERROR(MasterData!$D49,"") | T49: =IFERROR(MasterData!$E49,"") | U49: =IFERROR(MasterData!$F49,"") | V49: =IFERROR(MasterData!$I49,"") | W49: =IFERROR(MasterData!$H49,"")
A50: CLI-075-POS-003 | B50: Bastian | C50: Aggregator Manager | D50: Marketing & PR | E50: Mumbai | F50: Mid | G50: 46082 | I50: Hardik | J50: 1 | K50: Open | L50: Megh Replacement | M50: CLI-075 | N50: 0 | O50: =IF(J50="","",J50-N50) -> 1 | Q50: =IFERROR(MasterData!$B50,"") -> Nova | R50: =IFERROR(MasterData!$C50,"") -> HR | S50: =IFERROR(MasterData!$D50,"") | T50: =IFERROR(MasterData!$E50,"") | U50: =IFERROR(MasterData!$F50,"") | V50: =IFERROR(MasterData!$I50,"") | W50: =IFERROR(MasterData!$H50,"")
A51: CLI-075-POS-004 | B51: Bastian | C51: Graphic Designer | D51: Marketing & PR | E51: Mumbai | F51: Junior | G51: 46082 | I51: Aakash | J51: 1 | K51: Closed - Cancelled | M51: CLI-075 | N51: 0 | O51: =IF(J51="","",J51-N51) -> 1 | Q51: =IFERROR(MasterData!$B51,"") -> Ohris hospitality | R51: =IFERROR(MasterData!$C51,"") -> HR Head | S51: =IFERROR(MasterData!$D51,"") | T51: =IFERROR(MasterData!$E51,"") | U51: =IFERROR(MasterData!$F51,"") | V51: =IFERROR(MasterData!$I51,"") | W51: =IFERROR(MasterData!$H51,"")
A52: CLI-020-POS-001 | B52: Doppler | C52: Barista Head | D52: Bar & Beverages | E52: Jaipur | F52: Mid | G52: 46099 | I52: Manokamna | J52: 1 | K52: Open | M52: CLI-020 | N52: 0 | O52: =IF(J52="","",J52-N52) -> 1 | Q52: =IFERROR(MasterData!$B52,"") -> Olive | R52: =IFERROR(MasterData!$C52,"") -> HR Manager | S52: =IFERROR(MasterData!$D52,"") | T52: =IFERROR(MasterData!$E52,"") | U52: =IFERROR(MasterData!$F52,"") | V52: =IFERROR(MasterData!$I52,"") | W52: =IFERROR(MasterData!$H52,"")
A53: CLI-020-POS-002 | B53: Doppler | C53: Barista | D53: Bar & Beverages | E53: Jaipur | F53: Junior | G53: 46099 | I53: Manokamna | J53: 4 | K53: Open | L53: 1 for Matcha | M53: CLI-020 | N53: 0 | O53: =IF(J53="","",J53-N53) -> 4 | Q53: =IFERROR(MasterData!$B53,"") -> PSL | R53: =IFERROR(MasterData!$C53,"") -> Head Baker | S53: =IFERROR(MasterData!$D53,"") | T53: =IFERROR(MasterData!$E53,"") | U53: =IFERROR(MasterData!$F53,"") | V53: =IFERROR(MasterData!$I53,"") | W53: =IFERROR(MasterData!$H53,"")
A54: CLI-020-POS-003 | B54: Doppler | C54: Captain | D54: F&B - Service | E54: Jaipur | F54: Junior | G54: 46099 | I54: Manokamna | J54: 1 | K54: Open | M54: CLI-020 | N54: 0 | O54: =IF(J54="","",J54-N54) -> 1 | Q54: =IFERROR(MasterData!$B54,"") -> Pebble-Street | R54: =IFERROR(MasterData!$C54,"") -> Head Chef | S54: =IFERROR(MasterData!$D54,"") | T54: =IFERROR(MasterData!$E54,"") | U54: =IFERROR(MasterData!$F54,"") | V54: =IFERROR(MasterData!$I54,"") | W54: =IFERROR(MasterData!$H54,"")
A55: CLI-020-POS-004 | B55: Doppler | C55: F&B Associate | D55: F&B - Service | E55: Jaipur | F55: Junior | G55: 46099 | I55: Manokamna | J55: 3 | K55: Open | M55: CLI-020 | N55: 0 | O55: =IF(J55="","",J55-N55) -> 3 | Q55: =IFERROR(MasterData!$B55,"") -> Quetz | R55: =IFERROR(MasterData!$C55,"") -> Head GRE | S55: =IFERROR(MasterData!$D55,"") | T55: =IFERROR(MasterData!$E55,"") | U55: =IFERROR(MasterData!$F55,"") | V55: =IFERROR(MasterData!$I55,"") | W55: =IFERROR(MasterData!$H55,"")
A56: CLI-020-POS-005 | B56: Doppler | C56: Senior CDP | D56: F&B - Kitchen | E56: Jaipur | F56: Mid | G56: 46099 | I56: Manokamna | J56: 1 | K56: Closed - Filled | M56: CLI-020 | N56: 1 | O56: =IF(J56="","",J56-N56) -> 0 | Q56: =IFERROR(MasterData!$B56,"") -> Red turtle | R56: =IFERROR(MasterData!$C56,"") -> Hostess | S56: =IFERROR(MasterData!$D56,"") | T56: =IFERROR(MasterData!$E56,"") | U56: =IFERROR(MasterData!$F56,"") | V56: =IFERROR(MasterData!$I56,"") | W56: =IFERROR(MasterData!$H56,"")
A57: CLI-020-POS-006 | B57: Doppler | C57: Commi | D57: F&B - Kitchen | E57: Jaipur | F57: Junior | G57: 46099 | I57: Manokamna | J57: 1 | K57: Open | L57: 1 Commi 2 and 1 Commi 3 | M57: CLI-020 | N57: 0 | O57: =IF(J57="","",J57-N57) -> 1 | Q57: =IFERROR(MasterData!$B57,"") -> Ritika & Co. | R57: =IFERROR(MasterData!$C57,"") -> Junior Bartender | S57: =IFERROR(MasterData!$D57,"") | T57: =IFERROR(MasterData!$E57,"") | U57: =IFERROR(MasterData!$F57,"") | V57: =IFERROR(MasterData!$I57,"") | W57: =IFERROR(MasterData!$H57,"")
A58: CLI-020-POS-007 | B58: Doppler | C58: Kitchen Supervisor | D58: F&B - Kitchen | E58: Jaipur | F58: Junior | G58: 46099 | I58: Manokamna | J58: 1 | K58: Open | M58: CLI-020 | N58: 0 | O58: =IF(J58="","",J58-N58) -> 1 | Q58: =IFERROR(MasterData!$B58,"") -> Scarlett House | R58: =IFERROR(MasterData!$C58,"") -> Junior Sous Chef | S58: =IFERROR(MasterData!$D58,"") | T58: =IFERROR(MasterData!$E58,"") | U58: =IFERROR(MasterData!$F58,"") | V58: =IFERROR(MasterData!$I58,"") | W58: =IFERROR(MasterData!$H58,"")
A59: CLI-037-POS-001 | B59: Kohinoor Group | C59: OTA | D59: Other | E59: Mumbai | F59: Junior | G59: 46099 | I59: Manokamna | J59: 1 | K59: Open | M59: CLI-037 | N59: 0 | O59: =IF(J59="","",J59-N59) -> 1 | Q59: =IFERROR(MasterData!$B59,"") -> Shalimar | R59: =IFERROR(MasterData!$C59,"") -> Kitchen Helper | S59: =IFERROR(MasterData!$D59,"") | T59: =IFERROR(MasterData!$E59,"") | U59: =IFERROR(MasterData!$F59,"") | V59: =IFERROR(MasterData!$I59,"") | W59: =IFERROR(MasterData!$H59,"")
A60: CLI-037-POS-002 | B60: Kohinoor Group | C60: HR | D60: HR & Training | E60: Mumbai | F60: Junior | G60: 46099 | I60: Manokamna | J60: 1 | K60: Open | M60: CLI-037 | N60: 0 | O60: =IF(J60="","",J60-N60) -> 1 | Q60: =IFERROR(MasterData!$B60,"") -> Shalimar Hotel | R60: =IFERROR(MasterData!$C60,"") -> Kitchen Supervisor | S60: =IFERROR(MasterData!$D60,"") | T60: =IFERROR(MasterData!$E60,"") | U60: =IFERROR(MasterData!$F60,"") | V60: =IFERROR(MasterData!$I60,"") | W60: =IFERROR(MasterData!$H60,"")
A61: CLI-005-POS-004 | B61: All in | C61: Bartender | D61: Bar & Beverages | E61: Mumbai | F61: Junior | G61: 46101 | I61: Manokamna | J61: 5 | K61: Open | M61: CLI-005 | N61: 0 | O61: =IF(J61="","",J61-N61) -> 5 | Q61: =IFERROR(MasterData!$B61,"") -> Silver Train | R61: =IFERROR(MasterData!$C61,"") -> L&D | S61: =IFERROR(MasterData!$D61,"") | T61: =IFERROR(MasterData!$E61,"") | U61: =IFERROR(MasterData!$F61,"") | V61: =IFERROR(MasterData!$I61,"") | W61: =IFERROR(MasterData!$H61,"")
A62: CLI-014-POS-005 | B62: Blondie | C62: Barista | D62: Bar & Beverages | E62: Mumbai | F62: Mid | G62: 46104 | I62: Mohit | J62: 22 | K62: Open | L62: Barista & Senior Barista | M62: CLI-014 | N62: 0 | O62: =IF(J62="","",J62-N62) -> 22 | Q62: =IFERROR(MasterData!$B62,"") -> Sivako | R62: =IFERROR(MasterData!$C62,"") -> Marketing Manager | S62: =IFERROR(MasterData!$D62,"") | T62: =IFERROR(MasterData!$E62,"") | U62: =IFERROR(MasterData!$F62,"") | V62: =IFERROR(MasterData!$I62,"") | W62: =IFERROR(MasterData!$H62,"")
A63: CLI-001-POS-004 | B63: ABNAH | C63: Steward | D63: F&B - Service | E63: Mumbai | F63: Junior | G63: 46104 | I63: Mohit | J63: 5 | K63: Open | L63: Stewards | M63: CLI-001 | N63: 0 | O63: =IF(J63="","",J63-N63) -> 5 | Q63: =IFERROR(MasterData!$B63,"") -> Slink and Bardot | R63: =IFERROR(MasterData!$C63,"") -> Mixologist | S63: =IFERROR(MasterData!$D63,"") | T63: =IFERROR(MasterData!$E63,"") | U63: =IFERROR(MasterData!$F63,"") | V63: =IFERROR(MasterData!$I63,"") | W63: =IFERROR(MasterData!$H63,"")
A64: CLI-014-POS-006 | B64: Blondie | C64: F&B Associate | D64: F&B - Service | E64: Mumbai | F64: Junior | G64: 46104 | I64: Mohit | J64: 10 | K64: Open | L64: Stewards,Asst Stewards | M64: CLI-014 | N64: 0 | O64: =IF(J64="","",J64-N64) -> 10 | Q64: =IFERROR(MasterData!$B64,"") -> Speciality | R64: =IFERROR(MasterData!$C64,"") -> OTA | S64: =IFERROR(MasterData!$D64,"") | T64: =IFERROR(MasterData!$E64,"") | U64: =IFERROR(MasterData!$F64,"") | V64: =IFERROR(MasterData!$I64,"") | W64: =IFERROR(MasterData!$H64,"")
A65: CLI-014-POS-007 | B65: Blondie | C65: FOE | D65: Operations | E65: Mumbai | F65: Junior | G65: 46104 | I65: Mohit | J65: 4 | K65: Open | L65: Hostess,GRE | M65: CLI-014 | N65: 0 | O65: =IF(J65="","",J65-N65) -> 4 | Q65: =IFERROR(MasterData!$B65,"") -> Splendour | R65: =IFERROR(MasterData!$C65,"") -> Operations Head | S65: =IFERROR(MasterData!$D65,"") | T65: =IFERROR(MasterData!$E65,"") | U65: =IFERROR(MasterData!$F65,"") | V65: =IFERROR(MasterData!$I65,"") | W65: =IFERROR(MasterData!$H65,"")
A66: CLI-075-POS-005 | B66: Bastian | C66: HR | D66: HR & Training | E66: Mumbai | F66: Junior | G66: 46095 | I66: Aakash | J66: 1 | K66: Open | L66: L&D Executive | M66: CLI-075 | N66: 0 | O66: =IF(J66="","",J66-N66) -> 1 | Q66: =IFERROR(MasterData!$B66,"") -> TAB | R66: =IFERROR(MasterData!$C66,"") -> Operations Manager | S66: =IFERROR(MasterData!$D66,"") | T66: =IFERROR(MasterData!$E66,"") | U66: =IFERROR(MasterData!$F66,"") | V66: =IFERROR(MasterData!$I66,"") | W66: =IFERROR(MasterData!$H66,"")
A67: CLI-075-POS-006 | B67: Bastian | C67: HR | D67: HR & Training | E67: Mumbai | F67: Junior | G67: 46101 | I67: Aakash | J67: 1 | K67: Open | L67: Payroll Executive | M67: CLI-075 | N67: 0 | O67: =IF(J67="","",J67-N67) -> 1 | Q67: =IFERROR(MasterData!$B67,"") -> TAT | R67: =IFERROR(MasterData!$C67,"") -> Other | S67: =IFERROR(MasterData!$D67,"") | T67: =IFERROR(MasterData!$E67,"") | U67: =IFERROR(MasterData!$F67,"") | V67: =IFERROR(MasterData!$I67,"") | W67: =IFERROR(MasterData!$H67,"")
A68: CLI-076-POS-001 | B68: Green Gains | C68: F&B Associate | D68: F&B - Service | E68: Mumbai | F68: Junior | G68: 46101 | I68: Aakash | J68: 6 | K68: Open | L68: Team Member | M68: CLI-076 | N68: 0 | O68: =IF(J68="","",J68-N68) -> 6 | Q68: =IFERROR(MasterData!$B68,"") -> The Hummingtree | R68: =IFERROR(MasterData!$C68,"") -> Outlet Manager | S68: =IFERROR(MasterData!$D68,"") | T68: =IFERROR(MasterData!$E68,"") | U68: =IFERROR(MasterData!$F68,"") | V68: =IFERROR(MasterData!$I68,"") | W68: =IFERROR(MasterData!$H68,"")
A69: CLI-034-POS-001 | B69: Izumi | C69: Bartender | D69: Bar & Beverages | E69: Hyderabad | F69: Mid | G69: 46102 | I69: Edwin | J69: 5 | K69: Open | L69: Bartender, Sr Bartender | M69: CLI-034 | N69: 0 | O69: =IF(J69="","",J69-N69) -> 5 | Q69: =IFERROR(MasterData!$B69,"") -> The Kin Hotel | R69: =IFERROR(MasterData!$C69,"") -> Outlet Supervisor | S69: =IFERROR(MasterData!$D69,"") | T69: =IFERROR(MasterData!$E69,"") | U69: =IFERROR(MasterData!$F69,"") | V69: =IFERROR(MasterData!$I69,"") | W69: =IFERROR(MasterData!$H69,"")
A70: CLI-034-POS-002 | B70: Izumi | C70: Steward | D70: F&B - Service | E70: Hyderabad | F70: Junior | G70: 46106 | I70: Edwin | J70: 3 | K70: Open | M70: CLI-034 | N70: 0 | O70: =IF(J70="","",J70-N70) -> 3 | Q70: =IFERROR(MasterData!$B70,"") -> The Nest | R70: =IFERROR(MasterData!$C70,"") -> PR | S70: =IFERROR(MasterData!$D70,"") | T70: =IFERROR(MasterData!$E70,"") | U70: =IFERROR(MasterData!$F70,"") | V70: =IFERROR(MasterData!$I70,"") | W70: =IFERROR(MasterData!$H70,"")
A71: CLI-034-POS-003 | B71: Izumi | C71: Captain | D71: F&B - Service | E71: Hyderabad | F71: Junior | G71: 46106 | I71: Edwin | J71: 3 | K71: Open | M71: CLI-034 | N71: 0 | O71: =IF(J71="","",J71-N71) -> 3 | Q71: =IFERROR(MasterData!$B71,"") -> The Ranch | R71: =IFERROR(MasterData!$C71,"") -> PR Executive | S71: =IFERROR(MasterData!$D71,"") | T71: =IFERROR(MasterData!$E71,"") | U71: =IFERROR(MasterData!$F71,"") | V71: =IFERROR(MasterData!$I71,"") | W71: =IFERROR(MasterData!$H71,"")
A72: CLI-039-POS-001 | B72: Le 15 | C72: Receptionist | D72: Store & Purchase | E72: Mumbai | F72: Junior | G72: 46106 | I72: Mohit | J72: 1 | K72: Open | L72: Order taking,Packaging | M72: CLI-039 | N72: 0 | O72: =IF(J72="","",J72-N72) -> 1 | Q72: =IFERROR(MasterData!$B72,"") -> Tropicool | R72: =IFERROR(MasterData!$C72,"") -> Packaging Assistant | S72: =IFERROR(MasterData!$D72,"") | T72: =IFERROR(MasterData!$E72,"") | U72: =IFERROR(MasterData!$F72,"") | V72: =IFERROR(MasterData!$I72,"") | W72: =IFERROR(MasterData!$H72,"")
A73: CLI-039-POS-002 | B73: Le 15 | C73: Commi 2 | D73: F&B - Kitchen | E73: Mumbai | F73: Junior | G73: 46106 | I73: Mohit | J73: 2 | K73: Open | L73: Eggs,Sandwiches | M73: CLI-039 | N73: 0 | O73: =IF(J73="","",J73-N73) -> 2 | Q73: =IFERROR(MasterData!$B73,"") -> True palate | R73: =IFERROR(MasterData!$C73,"") -> Payroll | S73: =IFERROR(MasterData!$D73,"") | T73: =IFERROR(MasterData!$E73,"") | U73: =IFERROR(MasterData!$F73,"") | V73: =IFERROR(MasterData!$I73,"") | W73: =IFERROR(MasterData!$H73,"")
A74: CLI-039-POS-003 | B74: Le 15 | C74: Commi 2 | D74: F&B - Kitchen | E74: Mumbai | F74: Mid | G74: 46106 | I74: Mohit | J74: 1 | K74: Open | L74: Macroons | M74: CLI-039 | N74: 0 | O74: =IF(J74="","",J74-N74) -> 1 | Q74: =IFERROR(MasterData!$B74,"") -> UGIPL | R74: =IFERROR(MasterData!$C74,"") -> Purchase | S74: =IFERROR(MasterData!$D74,"") | T74: =IFERROR(MasterData!$E74,"") | U74: =IFERROR(MasterData!$F74,"") | V74: =IFERROR(MasterData!$I74,"") | W74: =IFERROR(MasterData!$H74,"")
A75: CLI-039-POS-004 | B75: Le 15 | C75: Barista | D75: F&B - Service | E75: Mumbai | F75: Junior | G75: 46106 | I75: Mohit | J75: 1 | K75: Open | L75: Basic Coffee making | M75: CLI-039 | N75: 0 | O75: =IF(J75="","",J75-N75) -> 1 | Q75: =IFERROR(MasterData!$B75,"") -> Zima | R75: =IFERROR(MasterData!$C75,"") -> QC | S75: =IFERROR(MasterData!$D75,"") | T75: =IFERROR(MasterData!$E75,"") | U75: =IFERROR(MasterData!$F75,"") | V75: =IFERROR(MasterData!$I75,"") | W75: =IFERROR(MasterData!$H75,"")
A76: CLI-050-POS-001 | B76: PSL | C76: Other | D76: F&B - Kitchen | E76: Mumbai | F76: Junior | G76: 46107 | I76: Edwin | J76: 1 | K76: Closed - Filled | M76: CLI-050 | N76: 1 | O76: =IF(J76="","",J76-N76) -> 0 | Q76: =IFERROR(MasterData!$B76,"") -> HNH Salad | R76: =IFERROR(MasterData!$C76,"") -> RM | S76: =IFERROR(MasterData!$D76,"") | T76: =IFERROR(MasterData!$E76,"") | U76: =IFERROR(MasterData!$F76,"") | V76: =IFERROR(MasterData!$I76,"") | W76: =IFERROR(MasterData!$H76,"")
A77: CLI-005-POS-005 | B77: All in | C77: EA | D77: Other | E77: Mumbai | F77: Mid | G77: 46107 | I77: Manokamna | J77: 1 | K77: Open | M77: CLI-005 | N77: 0 | O77: =IF(J77="","",J77-N77) -> 1 | Q77: =IFERROR(MasterData!$B77,"") -> Apero by Malvika | R77: =IFERROR(MasterData!$C77,"") -> Receptionist | S77: =IFERROR(MasterData!$D77,"") | T77: =IFERROR(MasterData!$E77,"") | U77: =IFERROR(MasterData!$F77,"") | V77: =IFERROR(MasterData!$I77,"") | W77: =IFERROR(MasterData!$H77,"")
B78: Blondie | C78: Commi | D78: F&B - Kitchen | E78: Mumbai | F78: Mid | G78: 46107 | I78: Mohit | J78: 3 | K78: Open | L78: Dosa & South Indian Chef | M78: CLI-006 | N78: 0 | O78: =IF(J78="","",J78-N78) -> 3 | Q78: =IFERROR(MasterData!$B78,"") -> Bastian | R78: =IFERROR(MasterData!$C78,"") -> Room Sales | S78: =IFERROR(MasterData!$D78,"") | T78: =IFERROR(MasterData!$E78,"") | U78: =IFERROR(MasterData!$F78,"") | V78: =IFERROR(MasterData!$I78,"") | W78: =IFERROR(MasterData!$H78,"")
B79: All in | C79: HR Manager | D79: HR & Training | E79: Mumbai | F79: Mid | G79: 46111 | I79: Manokamna | J79: 1 | K79: Open | M79: CLI-007 | N79: 0 | O79: =IF(J79="","",J79-N79) -> 1 | Q79: =IFERROR(MasterData!$B79,"") -> Green Gains | R79: =IFERROR(MasterData!$C79,"") -> SCM Head | S79: =IFERROR(MasterData!$D79,"") | T79: =IFERROR(MasterData!$E79,"") | U79: =IFERROR(MasterData!$F79,"") | V79: =IFERROR(MasterData!$I79,"") | W79: =IFERROR(MasterData!$H79,"")
B80: All in | C80: Sales | D80: Sales & Revenue | E80: Mumbai | F80: Mid | G80: 46111 | I80: Manokamna | J80: 1 | K80: Open | Q80: =IFERROR(MasterData!$B80,"") -> SLH | R80: =IFERROR(MasterData!$C80,"") -> Sales | S80: =IFERROR(MasterData!$D80,"") | T80: =IFERROR(MasterData!$E80,"") | U80: =IFERROR(MasterData!$F80,"") | V80: =IFERROR(MasterData!$I80,"") | W80: =IFERROR(MasterData!$H80,"")
B81: ABNAH | C81: Commi 1 | D81: F&B - Kitchen | E81: Mumbai | F81: Mid | G81: 46112 | I81: Mohit | J81: 3 | K81: Open | L81: Continental Food | Q81: =IFERROR(MasterData!$B81,"") -> Niko | R81: =IFERROR(MasterData!$C81,"") -> Senior Barista | S81: =IFERROR(MasterData!$D81,"") | T81: =IFERROR(MasterData!$E81,"") | U81: =IFERROR(MasterData!$F81,"") | V81: =IFERROR(MasterData!$I81,"") | W81: =IFERROR(MasterData!$H81,"")
B82: ABNAH | C82: Commi 1 | D82: F&B - Kitchen | E82: Mumbai | F82: Mid | G82: 46112 | I82: Mohit | J82: 3 | K82: Open | L82: Baker Chef - Breads | Q82: =IFERROR(MasterData!$B82,"") -> Courtside | R82: =IFERROR(MasterData!$C82,"") -> Senior Bartender | S82: =IFERROR(MasterData!$D82,"") | T82: =IFERROR(MasterData!$E82,"") | U82: =IFERROR(MasterData!$F82,"") | V82: =IFERROR(MasterData!$I82,"") | W82: =IFERROR(MasterData!$H82,"")
B83: ABNAH | C83: Sous Chef | D83: F&B - Kitchen | E83: Mumbai | F83: Senior | G83: 46112 | I83: Mohit | J83: 1 | K83: Open | L83: Sous Chef - Bakery | Q83: =IFERROR(MasterData!$B83,"") -> Penang Table | R83: =IFERROR(MasterData!$C83,"") -> Senior CDP | S83: =IFERROR(MasterData!$D83,"") | T83: =IFERROR(MasterData!$E83,"") | U83: =IFERROR(MasterData!$F83,"") | V83: =IFERROR(MasterData!$I83,"") | W83: =IFERROR(MasterData!$H83,"")
B84: Blondie | C84: Commi 1 | D84: F&B - Kitchen | E84: Mumbai | F84: Mid | G84: 46113 | I84: Mohit | J84: 3 | K84: Open | L84: Commi 1- Tandoor | Q84: =IFERROR(MasterData!$B84,"") -> TGC | R84: =IFERROR(MasterData!$C84,"") -> Senior Captain | S84: =IFERROR(MasterData!$D84,"") | T84: =IFERROR(MasterData!$E84,"") | U84: =IFERROR(MasterData!$F84,"") | V84: =IFERROR(MasterData!$I84,"") | W84: =IFERROR(MasterData!$H84,"")
B85: Blondie | C85: Commi 3 | D85: F&B - Kitchen | E85: Mumbai | F85: Mid | G85: 46113 | I85: Mohit | J85: 3 | K85: Open | L85: Commi 3- Chaat Section | Q85: =IFERROR(MasterData!$B85,"") -> Corleone's | R85: =IFERROR(MasterData!$C85,"") -> Senior GRE | S85: =IFERROR(MasterData!$D85,"") | T85: =IFERROR(MasterData!$E85,"") | U85: =IFERROR(MasterData!$F85,"") | V85: =IFERROR(MasterData!$I85,"") | W85: =IFERROR(MasterData!$H85,"")
B86: Blondie | C86: Sous Chef | D86: F&B - Kitchen | E86: Ahmedabad | F86: Senior | G86: 46118 | I86: Mohit | J86: 1 | K86: Open | L86: Sous Chef - Sushi | Q86: =IFERROR(MasterData!$B86,"") -> Nenapu | R86: =IFERROR(MasterData!$C86,"") -> Senior Sous Chef | S86: =IFERROR(MasterData!$D86,"") | T86: =IFERROR(MasterData!$E86,"") | U86: =IFERROR(MasterData!$F86,"") | V86: =IFERROR(MasterData!$I86,"") | W86: =IFERROR(MasterData!$H86,"")
B87: Blondie | C87: Sous Chef | D87: F&B - Kitchen | E87: Ahmedabad | F87: Senior | G87: 46118 | I87: Mohit | J87: 1 | K87: Open | L87: Sous Chef - Dimsum | Q87: =IFERROR(MasterData!$B87,"") | R87: =IFERROR(MasterData!$C87,"") -> Senior Steward | S87: =IFERROR(MasterData!$D87,"") | T87: =IFERROR(MasterData!$E87,"") | U87: =IFERROR(MasterData!$F87,"") | V87: =IFERROR(MasterData!$I87,"") | W87: =IFERROR(MasterData!$H87,"")
B88: Blondie | C88: Junior Sous Chef | D88: F&B - Kitchen | E88: Ahmedabad | F88: Senior | G88: 46118 | I88: Mohit | J88: 1 | K88: Open | L88: Junior Sous - Sushi | Q88: =IFERROR(MasterData!$B88,"") | R88: =IFERROR(MasterData!$C88,"") -> Social Media Manager | S88: =IFERROR(MasterData!$D88,"") | T88: =IFERROR(MasterData!$E88,"") | U88: =IFERROR(MasterData!$F88,"") | V88: =IFERROR(MasterData!$I88,"") | W88: =IFERROR(MasterData!$H88,"")
B89: Blondie | C89: Junior Sous Chef | D89: F&B - Kitchen | E89: Ahmedabad | F89: Senior | G89: 46118 | I89: Mohit | J89: 1 | K89: Open | L89: junior Sous - Dimsum | Q89: =IFERROR(MasterData!$B89,"") | R89: =IFERROR(MasterData!$C89,"") -> Sommelier | S89: =IFERROR(MasterData!$D89,"") | T89: =IFERROR(MasterData!$E89,"") | U89: =IFERROR(MasterData!$F89,"") | V89: =IFERROR(MasterData!$I89,"") | W89: =IFERROR(MasterData!$H89,"")
B90: Blondie | C90: CDP | D90: F&B - Kitchen | E90: Ahmedabad | F90: Mid | G90: 46118 | I90: Mohit | J90: 2 | K90: Open | L90: CDP - Sushi & Dimsum | Q90: =IFERROR(MasterData!$B90,"") | R90: =IFERROR(MasterData!$C90,"") -> Sous Chef | S90: =IFERROR(MasterData!$D90,"") | T90: =IFERROR(MasterData!$E90,"") | U90: =IFERROR(MasterData!$F90,"") | V90: =IFERROR(MasterData!$I90,"") | W90: =IFERROR(MasterData!$H90,"")
B91: ABNAH | C91: CDP | D91: F&B - Kitchen | E91: Mumbai | F91: Senior | G91: 46121 | I91: Mohit | J91: 3 | K91: Open | L91: CDP - Continental | Q91: =IFERROR(MasterData!$B91,"") | R91: =IFERROR(MasterData!$C91,"") -> Sr. Duty Manager | S91: =IFERROR(MasterData!$D91,"") | T91: =IFERROR(MasterData!$E91,"") | U91: =IFERROR(MasterData!$F91,"") | V91: =IFERROR(MasterData!$I91,"") | W91: =IFERROR(MasterData!$H91,"")
B92: ABNAH | C92: DCDP | D92: F&B - Kitchen | E92: Mumbai | F92: Mid | G92: 46121 | I92: Mohit | J92: 4 | K92: Open | L92: DCDP - Continental | Q92: =IFERROR(MasterData!$B92,"") | R92: =IFERROR(MasterData!$C92,"") -> Steward | S92: =IFERROR(MasterData!$D92,"") | T92: =IFERROR(MasterData!$E92,"") | U92: =IFERROR(MasterData!$F92,"") | V92: =IFERROR(MasterData!$I92,"") | W92: =IFERROR(MasterData!$H92,"")
... B96: ABNAH | C96: GRE | D96: Front Office & Rooms | E96: Mumbai | F96: Junior | G96: 46121 | I96: Mohit | J96: 3 | K96: Open | L96: Host , Hostess & GRE | Q96: =IFERROR(MasterData!$B96,"") | R96: =IFERROR(MasterData!$C96,"") -> Supply Chain | S96: =IFERROR(MasterData!$D96,"") | T96: =IFERROR(MasterData!$E96,"") | U96: =IFERROR(MasterData!$F96,"") | V96: =IFERROR(MasterData!$I96,"") | W96: =IFERROR(MasterData!$H96,"")
B97: Milagro (SLH) | C97: RM | D97: F&B - Service | E97: Mumbai | F97: Senior | G97: 46121 | I97: Hardik | J97: 1 | K97: Open | Q97: =IFERROR(MasterData!$B97,"") | R97: =IFERROR(MasterData!$C97,"") -> Team Leader | S97: =IFERROR(MasterData!$D97,"") | T97: =IFERROR(MasterData!$E97,"") | U97: =IFERROR(MasterData!$F97,"") | V97: =IFERROR(MasterData!$I97,"") | W97: =IFERROR(MasterData!$H97,"")
B98: Milagro (SLH) | C98: ARM | D98: F&B - Service | E98: Mumbai | F98: Mid | G98: 46121 | I98: Hardik | J98: 2 | K98: Open | Q98: =IFERROR(MasterData!$B98,"") | R98: =IFERROR(MasterData!$C98,"") -> Trainee Captain | S98: =IFERROR(MasterData!$D98,"") | T98: =IFERROR(MasterData!$E98,"") | U98: =IFERROR(MasterData!$F98,"") | V98: =IFERROR(MasterData!$I98,"") | W98: =IFERROR(MasterData!$H98,"")
B99: Milagro (SLH) | C99: Mixologist | D99: F&B - Service | E99: Mumbai | F99: Mid | G99: 46121 | I99: Hardik | J99: 1 | K99: Open | Q99: =IFERROR(MasterData!$B99,"") | R99: =IFERROR(MasterData!$C99,"") -> Training Manager | S99: =IFERROR(MasterData!$D99,"") | T99: =IFERROR(MasterData!$E99,"") | U99: =IFERROR(MasterData!$F99,"") | V99: =IFERROR(MasterData!$I99,"") | W99: =IFERROR(MasterData!$H99,"")
B100: Niko | C100: Executive Chef | D100: F&B - Kitchen | E100: Delhi | F100: Leadership | G100: 46115 | I100: Hardik | J100: 1 | K100: Closed - Filled | Q100: =IFERROR(MasterData!$B100,"") | R100: =IFERROR(MasterData!$C100,"") -> Waiter | S100: =IFERROR(MasterData!$D100,"") | T100: =IFERROR(MasterData!$E100,"") | U100: =IFERROR(MasterData!$F100,"") | V100: =IFERROR(MasterData!$I100,"") | W100: =IFERROR(MasterData!$H100,"")
B101: Niko | C101: Sous Chef | D101: F&B - Kitchen | E101: Delhi | F101: Senior | G101: 46121 | I101: Hardik | J101: 1 | K101: Open | Q101: =IFERROR(MasterData!$B101,"") | R101: =IFERROR(MasterData!$C101,"") -> Aggregator Manager | S101: =IFERROR(MasterData!$D101,"") | T101: =IFERROR(MasterData!$E101,"") | U101: =IFERROR(MasterData!$F101,"") | V101: =IFERROR(MasterData!$I101,"") | W101: =IFERROR(MasterData!$H101,"")
B102: Niko | C102: CDP | D102: F&B - Kitchen | E102: Delhi | F102: Mid | G102: 46121 | I102: Hardik | J102: 1 | K102: Open | Q102: =IFERROR(MasterData!$B102,"") | R102: =IFERROR(MasterData!$C102,"") -> Graphic Designer | S102: =IFERROR(MasterData!$D102,"") | T102: =IFERROR(MasterData!$E102,"") | U102: =IFERROR(MasterData!$F102,"") | V102: =IFERROR(MasterData!$I102,"") | W102: =IFERROR(MasterData!$H102,"")
B103: Bastian | C103: Bar Manager | D103: F&B - Service | E103: Ahmedabad | F103: Senior | G103: 46132 | I103: Mohit | J103: 1 | K103: Open | L103: Bar Manager - Mocktail Bar | Q103: =IFERROR(MasterData!$B103,"") | R103: =IFERROR(MasterData!$C103,"") -> Barista | S103: =IFERROR(MasterData!$D103,"") | T103: =IFERROR(MasterData!$E103,"") | U103: =IFERROR(MasterData!$F103,"") | V103: =IFERROR(MasterData!$I103,"") | W103: =IFERROR(MasterData!$H103,"")
...

Sheet Candidate Pipeline
A1: 👤 CANDIDATE PIPELINE
A2: 💡 DB Cand ID links back to the Candidate Database. Select Client Name → Client ID auto-fills. Pipeline Cand ID auto-generates.
A3: Pipeline ID | B3: DB Cand ID | C3: Candidate Name | D3: Client Name | E3: Client ID | F3: Role Applied For | G3: Current Company | H3: City | I3: Stage | J3: Sourced By | K3: Date Added | L3: Last Updated | M3: Next Follow-up | N3: Client Feedback | O3: Remarks
A4: PIP-001 | B4: CAN-007 | C4: Lakshita Shaw | D4: Hunger Inc | E4: CLI-031 | F4: Steward | G4: Love & Latte Juhu | H4: Mumbai | I4: Candidate Dropped | J4: Edwin | K4: 46104 | P4: =IFERROR(MasterData!$B4,"") -> ABNAH | Q4: =IFERROR(MasterData!$C4,"") -> ARM | R4: =IFERROR(MasterData!$E4,"") -> Mumbai | S4: =IFERROR(MasterData!$G4,"") -> Sent to Client | T4: =IFERROR(MasterData!$I4,"") -> Edwin
A5: PIP-002 | C5: Keval Javadia | D5: Hunger Inc | E5: CLI-031 | F5: F&B Executive | G5: Baang | H5: Mumbai | I5: Rejected | J5: Mohit | K5: 46104 | P5: =IFERROR(MasterData!$B5,"") -> Abhinav Immigration | Q5: =IFERROR(MasterData!$C5,"") -> Assistant Bartender | R5: =IFERROR(MasterData!$E5,"") -> Delhi | S5: =IFERROR(MasterData!$G5,"") -> Interview Scheduled | T5: =IFERROR(MasterData!$I5,"") -> Manokamna
A6: PIP-003 | C6: Vedant Nimbre | D6: Hunger Inc | E6: CLI-031 | F6: Steward | G6: Rahega | H6: Mumbai | I6: Joined | J6: Mohit | K6: 46104 | P6: =IFERROR(MasterData!$B6,"") -> Adarsh Sweets | Q6: =IFERROR(MasterData!$C6,"") -> Assistant Front Office Manager | R6: =IFERROR(MasterData!$E6,"") -> Bangalore | S6: =IFERROR(MasterData!$G6,"") -> Result Awaited | T6: =IFERROR(MasterData!$I6,"") -> Hardik
A7: PIP-004 | C7: Priya Jerome Gonsalves | D7: Blondie | E7: CLI-014 | F7: FOE | G7: Fresher | H7: Mumbai | I7: Candidate Dropped | J7: Mohit | K7: 46104 | L7: 46104 | P7: =IFERROR(MasterData!$B7,"") -> Agarwal Biryani | Q7: =IFERROR(MasterData!$C7,"") -> Assistant Manager | R7: =IFERROR(MasterData!$E7,"") -> Hyderabad | S7: =IFERROR(MasterData!$G7,"") -> Selected | T7: =IFERROR(MasterData!$I7,"") -> Mohit
A8: PIP-005 | C8: Aarti Rokade | D8: Le 15 | E8: CLI-031 | F8: Barista | G8: Not working | H8: Mumbai | I8: Rejected | J8: Mohit | K8: 46104 | P8: =IFERROR(MasterData!$B8,"") -> All in | Q8: =IFERROR(MasterData!$C8,"") -> Assistant Outlet Manager | R8: =IFERROR(MasterData!$E8,"") -> Pune | S8: =IFERROR(MasterData!$G8,"") -> Rejected | T8: =IFERROR(MasterData!$I8,"") -> Aakash
A9: PIP-006 | C9: Sanskrita Ekawade | D9: Doppler | E9: CLI-020 | F9: Senior Barista | G9: Starbucks | H9: Mumbai | I9: Rejected | J9: Mohit | K9: 46104 | P9: =IFERROR(MasterData!$B9,"") -> Aria Communication | Q9: =IFERROR(MasterData!$C9,"") -> Assistant Stores Manager | R9: =IFERROR(MasterData!$E9,"") -> Goa | S9: =IFERROR(MasterData!$G9,"") -> Hold | T9: =IFERROR(MasterData!$I9,"")
A10: PIP-007 | C10: Chetan Medhekar | D10: Doppler | E10: CLI-020 | F10: Senior Barista | G10: Bouee Coffee Roasters | H10: Gujarat | I10: Rejected | J10: Mohit | K10: 46104 | P10: =IFERROR(MasterData!$B10,"") -> Atmosphere | Q10: =IFERROR(MasterData!$C10,"") -> Asst Cafe Manager | R10: =IFERROR(MasterData!$E10,"") -> Chennai | S10: =IFERROR(MasterData!$G10,"") -> Offer Sent | T10: =IFERROR(MasterData!$I10,"")
A11: PIP-008 | C11: Sangram Patil | D11: Neighbourhood | E11: CLI-045 | F11: Sous Chef | G11: None | H11: Mumbai | I11: Candidate Dropped | J11: Mohit | K11: 46104 | P11: =IFERROR(MasterData!$B11,"") -> August Café | Q11: =IFERROR(MasterData!$C11,"") -> Bar Lead | R11: =IFERROR(MasterData!$E11,"") -> Kolkata | S11: =IFERROR(MasterData!$G11,"") -> Offer Accepted | T11: =IFERROR(MasterData!$I11,"")
A12: PIP-009 | C12: Prajwal Sawant | D12: Blondie | E12: CLI-014 | F12: Commi 2 | G12: None | H12: Mumbai | I12: Candidate Dropped | J12: Mohit | K12: 46104 | P12: =IFERROR(MasterData!$B12,"") -> Aures hospitality | Q12: =IFERROR(MasterData!$C12,"") -> Bar Manager | R12: =IFERROR(MasterData!$E12,"") -> Ahmedabad | S12: =IFERROR(MasterData!$G12,"") -> Joined | T12: =IFERROR(MasterData!$I12,"")
A13: PIP-010 | C13: Ainul Khan | D13: Blondie | E13: CLI-014 | F13: Sous Chef | G13: The Oberoi,Mumbai | H13: Mumbai | I13: Offer Accepted | J13: Mohit | K13: 46104 | P13: =IFERROR(MasterData!$B13,"") -> BB | Q13: =IFERROR(MasterData!$C13,"") -> Bar Supervisor | R13: =IFERROR(MasterData!$E13,"") -> Jaipur | S13: =IFERROR(MasterData!$G13,"") -> Candidate Dropped | T13: =IFERROR(MasterData!$I13,"")
A14: PIP-011 | C14: Mihir Bagwe | D14: Blondie | E14: CLI-014 | F14: Commi 2 | G14: None | H14: Mumbai | I14: Candidate Dropped | J14: Mohit | K14: 46104 | P14: =IFERROR(MasterData!$B14,"") -> BTC | Q14: =IFERROR(MasterData!$C14,"") -> Barback | R14: =IFERROR(MasterData!$E14,"") -> Other | S14: =IFERROR(MasterData!$G14,"") | T14: =IFERROR(MasterData!$I14,"")
A15: PIP-012 | C15: Khuhbu Magar | D15: Bastian | E15: CLI-075 | F15: HR | G15: Milagro | H15: Mumbai | I15: Rejected | J15: Mohit | K15: 46104 | P15: =IFERROR(MasterData!$B15,"") -> Baesic Fit | Q15: =IFERROR(MasterData!$C15,"") -> Barista | R15: =IFERROR(MasterData!$E15,"") | S15: =IFERROR(MasterData!$G15,"") | T15: =IFERROR(MasterData!$I15,"")
A16: PIP-013 | C16: Pushkaraj Gurav | D16: Hunger Inc | E16: CLI-031 | F16: Captain | G16: Trident,Nariman Point | H16: Mumbai | I16: Rejected | J16: Mohit | K16: 46104 | P16: =IFERROR(MasterData!$B16,"") -> Bare | Q16: =IFERROR(MasterData!$C16,"") -> Barista Head | R16: =IFERROR(MasterData!$E16,"") | S16: =IFERROR(MasterData!$G16,"") | T16: =IFERROR(MasterData!$I16,"")
A17: PIP-014 | C17: Nishant Kadam | D17: ABNAH | E17: CLI-001 | F17: Bartender | G17: None | H17: Mumbai | I17: Rejected | J17: Mohit | K17: 46105 | P17: =IFERROR(MasterData!$B17,"") -> Blondie | Q17: =IFERROR(MasterData!$C17,"") -> Barista Trainer | R17: =IFERROR(MasterData!$E17,"") | S17: =IFERROR(MasterData!$G17,"") | T17: =IFERROR(MasterData!$I17,"")
D18: Speciality | E18: CLI-061 | F18: General Manager | G18: Fratterniti/EHV | H18: Delhi | I18: Interview Scheduled | J18: Hardik | K18: 46104 | L18: 46107 | M18: 46107 | P18: =IFERROR(MasterData!$B18,"") -> Circa 11 | Q18: =IFERROR(MasterData!$C18,"") -> Bartender | R18: =IFERROR(MasterData!$E18,"") | S18: =IFERROR(MasterData!$G18,"") | T18: =IFERROR(MasterData!$I18,"")
A19: PIP-016 | C19: Prakash Pradhan | D19: Speciality | E19: CLI-061 | F19: Head Chef | G19: Massive | H19: Delhi | I19: Selected | J19: Hardik | K19: 46104 | L19: 46104 | M19: 46109 | P19: =IFERROR(MasterData!$B19,"") -> CocoCart | Q19: =IFERROR(MasterData!$C19,"") -> CDP | R19: =IFERROR(MasterData!$E19,"") | S19: =IFERROR(MasterData!$G19,"") | T19: =IFERROR(MasterData!$I19,"")
A20: PIP-017 | B20: CAN-008 | C20: Akhil Chavan | D20: Izumi | E20: CLI-034 | F20: Bartender | G20: Impressario | H20: Hyderabad | I20: Offer Accepted | J20: Edwin | K20: 46105 | L20: 46105 | P20: =IFERROR(MasterData!$B20,"") -> DU Hospitality | Q20: =IFERROR(MasterData!$C20,"") -> CRM | R20: =IFERROR(MasterData!$E20,"") | S20: =IFERROR(MasterData!$G20,"") | T20: =IFERROR(MasterData!$I20,"")
A21: PIP-018 | B21: CAN-009 | C21: Saurabh Vengurlekar | D21: Hunger Inc | E21: CLI-031 | F21: Head Chef | G21: Cantina | H21: Mumbai | I21: Sent to Client | J21: Edwin | K21: 46105 | P21: =IFERROR(MasterData!$B21,"") -> Diva | Q21: =IFERROR(MasterData!$C21,"") -> Cafe Manager | R21: =IFERROR(MasterData!$E21,"") | S21: =IFERROR(MasterData!$G21,"") | T21: =IFERROR(MasterData!$I21,"")
A22: PIP-019 | C22: Prasad Parab | D22: ABNAH | E22: CLI-001 | F22: Bartender | G22: Foo | H22: Mumbai | I22: Rejected | J22: Mohit | K22: 46106 | P22: =IFERROR(MasterData!$B22,"") -> Donmai | Q22: =IFERROR(MasterData!$C22,"") -> Cafe Supervisor | R22: =IFERROR(MasterData!$E22,"") | S22: =IFERROR(MasterData!$G22,"") | T22: =IFERROR(MasterData!$I22,"")
A23: PIP-020 | C23: Moin Pawar | D23: ABNAH | E23: CLI-039 | F23: Barista | G23: Mc Donalds | H23: Mumbai | I23: Joined | J23: Mohit | K23: 46105 | L23: 46106 | M23: 46112 | P23: =IFERROR(MasterData!$B23,"") -> Doppler | Q23: =IFERROR(MasterData!$C23,"") -> Captain | R23: =IFERROR(MasterData!$E23,"") | S23: =IFERROR(MasterData!$G23,"") | T23: =IFERROR(MasterData!$I23,"")
A24: PIP-021 | C24: Dinesh Nishad | D24: Courtside | E24: CLI-014 | F24: Commi 1 | G24: None | H24: Mumbai | I24: Candidate Dropped | J24: Aakash | K24: 46140 | L24: 46140 | M24: 46140 | P24: =IFERROR(MasterData!$B24,"") -> Dough and Joe | Q24: =IFERROR(MasterData!$C24,"") -> Cashier | R24: =IFERROR(MasterData!$E24,"") | S24: =IFERROR(MasterData!$G24,"") | T24: =IFERROR(MasterData!$I24,"")
A25: PIP-022 | C25: Rashmi Walavalkar | D25: Courtside | E25: CLI-014 | F25: Commi 2 | G25: None | H25: Mumbai | I25: Candidate Dropped | J25: Aakash | K25: 46140 | L25: 46140 | M25: 46140 | P25: =IFERROR(MasterData!$B25,"") -> EDD | Q25: =IFERROR(MasterData!$C25,"") -> Chef | R25: =IFERROR(MasterData!$E25,"") | S25: =IFERROR(MasterData!$G25,"") | T25: =IFERROR(MasterData!$I25,"")
A26: PIP-023 | B26: CAN-033 | C26: Aarti Jaiswar | D26: Izumi | E26: CLI-034 | F26: Senior GRE | G26: ODE | H26: Mumbai | I26: Offer Accepted | J26: Edwin | K26: 46106 | L26: 46106 | P26: =IFERROR(MasterData!$B26,"") -> FHPL | Q26: =IFERROR(MasterData!$C26,"") -> Commi | R26: =IFERROR(MasterData!$E26,"") | S26: =IFERROR(MasterData!$G26,"") | T26: =IFERROR(MasterData!$I26,"")
A27: PIP-024 | C27: Pritam Bhindani | D27: Blondie | E27: CLI-014 | F27: Commi 2 | G27: Leela | H27: Mumbai | I27: Candidate Dropped | J27: Aakash | K27: 46106 | O27: DNR | P27: =IFERROR(MasterData!$B27,"") -> Flavour Pots | Q27: =IFERROR(MasterData!$C27,"") -> Commi 1 | R27: =IFERROR(MasterData!$E27,"") | S27: =IFERROR(MasterData!$G27,"") | T27: =IFERROR(MasterData!$I27,"")
A28: PIP-025 | C28: Purvi Mhambrey | D28: Bastian | E28: CLI-075 | F28: Social Media Manager | G28: TVA | H28: Mumbai | I28: Joined | J28: Aakash | K28: 46106 | M28: 46108 | P28: =IFERROR(MasterData!$B28,"") -> Food Square | Q28: =IFERROR(MasterData!$C28,"") -> Commi 2 | R28: =IFERROR(MasterData!$E28,"") | S28: =IFERROR(MasterData!$G28,"") | T28: =IFERROR(MasterData!$I28,"")
A29: PIP-026 | C29: Firoj Khan | D29: Doppler | E29: CLI-020 | F29: Captain | G29: Ananta Spa | H29: Jaipur | I29: Sent to Client | J29: Manokamna | K29: 46106 | P29: =IFERROR(MasterData!$B29,"") -> Foodmatters | Q29: =IFERROR(MasterData!$C29,"") -> Commi 3 | R29: =IFERROR(MasterData!$E29,"") | S29: =IFERROR(MasterData!$G29,"") | T29: =IFERROR(MasterData!$I29,"")
A30: PIP-027 | C30: Ami Desai | D30: Blondie | E30: CLI-014 | F30: Social Media Manager | G30: Bizspark ventures | H30: Mumbai | I30: Hold | J30: Aakash | K30: 46106 | M30: 46110 | P30: =IFERROR(MasterData!$B30,"") -> Ghostkitchens | Q30: =IFERROR(MasterData!$C30,"") -> Community Manager | R30: =IFERROR(MasterData!$E30,"") | S30: =IFERROR(MasterData!$G30,"") | T30: =IFERROR(MasterData!$I30,"")
A31: PIP-028 | C31: Trisha Karambar | D31: Blondie | E31: CLI-014 | F31: Social Media Manager | G31: Back Benchers Digital | H31: Mumbai | I31: Hold | J31: Aakash | K31: 46106 | M31: 46110 | P31: =IFERROR(MasterData!$B31,"") -> Gupta Brands | Q31: =IFERROR(MasterData!$C31,"") -> Content Strategist | R31: =IFERROR(MasterData!$E31,"") | S31: =IFERROR(MasterData!$G31,"") | T31: =IFERROR(MasterData!$I31,"")
A32: PIP-029 | C32: Omkar Shinde | D32: Milagro (SLH) | E32: CLI-014 | F32: Senior Barista | G32: Thee Wild Berry | H32: Mumbai | I32: Rejected | J32: Aakash | K32: 46106 | L32: 46133 | M32: 46133 | P32: =IFERROR(MasterData!$B32,"") -> Huddle and Score | Q32: =IFERROR(MasterData!$C32,"") -> Counter Sales | R32: =IFERROR(MasterData!$E32,"") | S32: =IFERROR(MasterData!$G32,"") | T32: =IFERROR(MasterData!$I32,"")
A33: PIP-030 | C33: Surendra Singh | D33: Doppler | E33: CLI-020 | F33: Captain | G33: St Regis | H33: Delhi | I33: Sent to Client | J33: Manokamna | K33: 46106 | P33: =IFERROR(MasterData!$B33,"") -> Hummingtree | Q33: =IFERROR(MasterData!$C33,"") -> DCDP | R33: =IFERROR(MasterData!$E33,"") | S33: =IFERROR(MasterData!$G33,"") | T33: =IFERROR(MasterData!$I33,"")
A34: PIP-031 | C34: Nengboi Haokip | D34: Blondie | E34: CLI-014 | F34: GRE | G34: Brunch and Cake | H34: Mumbai | I34: Candidate Dropped | J34: Aakash | K34: 46106 | O34: DNR | P34: =IFERROR(MasterData!$B34,"") -> Hunger Inc | Q34: =IFERROR(MasterData!$C34,"") -> Data Analyst | R34: =IFERROR(MasterData!$E34,"") | S34: =IFERROR(MasterData!$G34,"") | T34: =IFERROR(MasterData!$I34,"")
A35: PIP-032 | C35: Vinay Nair | D35: Donmai | E35: CLI-019 | F35: Commi 1 | G35: None | H35: Mumbai | I35: Candidate Dropped | J35: Aakash | K35: 46106 | L35: 46106 | M35: 46111 | O35: Persuing a different opportunity in Ahmedabad | P35: =IFERROR(MasterData!$B35,"") -> Idoru | Q35: =IFERROR(MasterData!$C35,"") -> Director of Operations | R35: =IFERROR(MasterData!$E35,"") | S35: =IFERROR(MasterData!$G35,"") | T35: =IFERROR(MasterData!$I35,"")
A36: PIP-033 | B36: CAN-037 | C36: Imli Longchari | D36: Izumi | E36: CLI-034 | F36: Senior Bartender | G36: Gunpowder | H36: Hyderabad | I36: Rejected | J36: Edwin | K36: 46106 | L36: 46106 | M36: 46107 | N36: Not upto the mark | O36: I have shared it with Circa 11 | P36: =IFERROR(MasterData!$B36,"") -> Ikai | Q36: =IFERROR(MasterData!$C36,"") -> Duty Manager | R36: =IFERROR(MasterData!$E36,"") | S36: =IFERROR(MasterData!$G36,"") | T36: =IFERROR(MasterData!$I36,"")
A37: PIP-034 | C37: Nadeem Merchant | D37: HNH Salad | E37: CLI-073 | F37: Purchase | H37: Mumbai | I37: Rejected | J37: Aakash | K37: 46106 | N37: Not upto the mark | P37: =IFERROR(MasterData!$B37,"") -> Izumi | Q37: =IFERROR(MasterData!$C37,"") -> EA | R37: =IFERROR(MasterData!$E37,"") | S37: =IFERROR(MasterData!$G37,"") | T37: =IFERROR(MasterData!$I37,"")
A38: PIP-035 | C38: Satish Jadhav | D38: HNH Salad | E38: CLI-073 | F38: Stores Manager | H38: Mumbai | I38: Rejected | J38: Aakash | K38: 46106 | P38: =IFERROR(MasterData!$B38,"") -> Izumi - GOA | Q38: =IFERROR(MasterData!$C38,"") -> Executive Chef | R38: =IFERROR(MasterData!$E38,"") | S38: =IFERROR(MasterData!$G38,"") | T38: =IFERROR(MasterData!$I38,"")
A39: PIP-036 | C39: Vikash Kumar | D39: Doppler | E39: CLI-020 | F39: Captain | G39: Hotel Cross Lane | H39: Other | I39: Candidate Dropped | J39: Aakash | K39: 46106 | P39: =IFERROR(MasterData!$B39,"") -> Kaia | Q39: =IFERROR(MasterData!$C39,"") -> F&B Associate | R39: =IFERROR(MasterData!$E39,"") | S39: =IFERROR(MasterData!$G39,"") | T39: =IFERROR(MasterData!$I39,"")
A40: PIP-037 | C40: Aquib Fayaz | D40: Doppler | E40: CLI-020 | F40: Senior Barista | G40: None | H40: Delhi | I40: Candidate Dropped | J40: Aakash | K40: 46106 | M40: 46108 | P40: =IFERROR(MasterData!$B40,"") -> Kohinoor Group | Q40: =IFERROR(MasterData!$C40,"") -> F&B Controller | R40: =IFERROR(MasterData!$E40,"") | S40: =IFERROR(MasterData!$G40,"") | T40: =IFERROR(MasterData!$I40,"")
A41: PIP-038 | C41: Rushikesh Chavan | D41: Bare | E41: CLI-013 | F41: Junior Sous Chef | G41: None | H41: Mumbai | I41: Hold | J41: Aakash | K41: 46106 | M41: 46107 | P41: =IFERROR(MasterData!$B41,"") -> La Loca Maria | Q41: =IFERROR(MasterData!$C41,"") -> F&B Executive | R41: =IFERROR(MasterData!$E41,"") | S41: =IFERROR(MasterData!$G41,"") | T41: =IFERROR(MasterData!$I41,"")
A42: PIP-039 | C42: Mahinoor Sayyed | D42: Green Gains | E42: CLI-076 | F42: Kitchen Helper | G42: None | H42: Mumbai | I42: Candidate Dropped | J42: Aakash | K42: 46106 | M42: 46107 | O42: DNR | P42: =IFERROR(MasterData!$B42,"") -> Le 15 | Q42: =IFERROR(MasterData!$C42,"") -> F&B Supervisor | R42: =IFERROR(MasterData!$E42,"") | S42: =IFERROR(MasterData!$G42,"") | T42: =IFERROR(MasterData!$I42,"")
A43: PIP-040 | C43: Yuvraj Singh | D43: ABNAH | E43: CLI-001 | F43: Bartender | G43: Jio | H43: Mumbai | I43: Candidate Dropped | J43: Aakash | K43: 46106 | L43: 46114 | M43: 46115 | O43: Joined Bombay Canteen | P43: =IFERROR(MasterData!$B43,"") -> Malsons | Q43: =IFERROR(MasterData!$C43,"") -> FOE | R43: =IFERROR(MasterData!$E43,"") | S43: =IFERROR(MasterData!$G43,"") | T43: =IFERROR(MasterData!$I43,"")
A44: PIP-041 | C44: Manish Sharma | D44: Speciality | E44: CLI-061 | F44: DCDP | G44: Tao Fu | H44: Pune | I44: Sent to Client | J44: Aakash | K44: 46106 | M44: 46111 | P44: =IFERROR(MasterData!$B44,"") -> Mia Cucina | Q44: =IFERROR(MasterData!$C44,"") -> Floor Supervisor | R44: =IFERROR(MasterData!$E44,"") | S44: =IFERROR(MasterData!$G44,"") | T44: =IFERROR(MasterData!$I44,"")
A45: PIP-042 | C45: Riya Surve | D45: Blondie | E45: CLI-014 | F45: Commi 1 | G45: None | H45: Mumbai | I45: Rejected | J45: Aakash | K45: 46106 | L45: 46120 | M45: 46121 | P45: =IFERROR(MasterData!$B45,"") -> Milagro (SLH) | Q45: =IFERROR(MasterData!$C45,"") -> Front Desk | R45: =IFERROR(MasterData!$E45,"") | S45: =IFERROR(MasterData!$G45,"") | T45: =IFERROR(MasterData!$I45,"")
A46: PIP-043 | C46: Gautam Karmakar | D46: Donmai | E46: CLI-019 | F46: Purchase | G46: Ditas | H46: Mumbai | I46: Candidate Dropped | J46: Mohit | K46: 46106 | P46: =IFERROR(MasterData!$B46,"") -> Monarch | Q46: =IFERROR(MasterData!$C46,"") -> GRE | R46: =IFERROR(MasterData!$E46,"") | S46: =IFERROR(MasterData!$G46,"") | T46: =IFERROR(MasterData!$I46,"")
A47: PIP-044 | C47: Aditya Purohit | D47: Blondie | E47: CLI-014 | F47: Senior CDP | G47: Personal Chef | H47: Mumbai | I47: Rejected | J47: Mohit | K47: 46106 | P47: =IFERROR(MasterData!$B47,"") -> NOTO | Q47: =IFERROR(MasterData!$C47,"") -> GRM | R47: =IFERROR(MasterData!$E47,"") | S47: =IFERROR(MasterData!$G47,"") | T47: =IFERROR(MasterData!$I47,"")
A48: PIP-045 | C48: Venkatesh Rathod | D48: Blondie | E48: CLI-014 | F48: Senior Barista | G48: None | H48: Mumbai | I48: Candidate Dropped | J48: Mohit | K48: 46106 | P48: =IFERROR(MasterData!$B48,"") -> Neighbourhood | Q48: =IFERROR(MasterData!$C48,"") -> General Manager | R48: =IFERROR(MasterData!$E48,"") | S48: =IFERROR(MasterData!$G48,"") | T48: =IFERROR(MasterData!$I48,"")
A49: PIP-046 | C49: Akash Dalui | D49: Blondie | E49: CLI-014 | F49: CDP | G49: The Oberoi,Mumbai | H49: Mumbai | I49: Candidate Dropped | J49: Mohit | K49: 46106 | P49: =IFERROR(MasterData!$B49,"") -> Nidhi and Mihir PR | Q49: =IFERROR(MasterData!$C49,"") -> HK Supervisor | R49: =IFERROR(MasterData!$E49,"") | S49: =IFERROR(MasterData!$G49,"") | T49: =IFERROR(MasterData!$I49,"")
A50: PIP-047 | B50: CAN-048 | C50: Saikumar Yatham | D50: Izumi | E50: CLI-034 | F50: Captain | G50: Palms, Jumeriah | H50: Hyderabad | I50: Interview Scheduled | J50: Edwin | K50: 46107 | P50: =IFERROR(MasterData!$B50,"") -> Nova | Q50: =IFERROR(MasterData!$C50,"") -> HR | R50: =IFERROR(MasterData!$E50,"") | S50: =IFERROR(MasterData!$G50,"") | T50: =IFERROR(MasterData!$I50,"")
A51: PIP-048 | B51: CAN-049 | C51: Harish Eppapali | D51: Izumi | E51: CLI-034 | F51: RM | G51: Mia Cuccina | H51: Mumbai | I51: Interview Scheduled | J51: Edwin | K51: 46107 | P51: =IFERROR(MasterData!$B51,"") -> Ohris hospitality | Q51: =IFERROR(MasterData!$C51,"") -> HR Head | R51: =IFERROR(MasterData!$E51,"") | S51: =IFERROR(MasterData!$G51,"") | T51: =IFERROR(MasterData!$I51,"")
A52: PIP-049 | B52: CAN-050 | C52: Dennis Hmangaizhzuala | D52: Izumi | E52: CLI-034 | F52: Captain | G52: Eatopia | H52: Mumbai | I52: Selected | J52: Edwin | K52: 46107 | P52: =IFERROR(MasterData!$B52,"") -> Olive | Q52: =IFERROR(MasterData!$C52,"") -> HR Manager | R52: =IFERROR(MasterData!$E52,"") | S52: =IFERROR(MasterData!$G52,"") | T52: =IFERROR(MasterData!$I52,"")
A53: PIP-050 | B53: CAN-051 | C53: Heena Kadavadkar | D53: PSL | E53: CLI-050 | F53: Other | G53: Toit | H53: Mumbai | I53: Joined | J53: Edwin | K53: 46107 | L53: 46107 | N53: Good at work | P53: =IFERROR(MasterData!$B53,"") -> PSL | Q53: =IFERROR(MasterData!$C53,"") -> Head Baker | R53: =IFERROR(MasterData!$E53,"") | S53: =IFERROR(MasterData!$G53,"") | T53: =IFERROR(MasterData!$I53,"")
A54: PIP-051 | B54: CAN-052 | C54: Sameer Khan | D54: Blondie | E54: CLI-051 | F54: Captain | G54: None | H54: Mumbai | I54: Joined | J54: Aakash | K54: 46107 | L54: 46111 | M54: 46112 | P54: =IFERROR(MasterData!$B54,"") -> Pebble-Street | Q54: =IFERROR(MasterData!$C54,"") -> Head Chef | R54: =IFERROR(MasterData!$E54,"") | S54: =IFERROR(MasterData!$G54,"") | T54: =IFERROR(MasterData!$I54,"")
A55: PIP-052 | B55: CAN-053 | C55: Sharnal Ronald Sequeira | D55: All in | E55: CLI-052 | F55: DCDP | G55: Inox | H55: Mumbai | I55: Interview Scheduled | J55: Aakash | K55: 46107 | L55: 46129 | M55: 46132 | P55: =IFERROR(MasterData!$B55,"") -> Quetz | Q55: =IFERROR(MasterData!$C55,"") -> Head GRE | R55: =IFERROR(MasterData!$E55,"") | S55: =IFERROR(MasterData!$G55,"") | T55: =IFERROR(MasterData!$I55,"")
A56: PIP-053 | C56: Mohan Kundu | D56: SLH | E56: CLI-053 | F56: Head Baker | G56: Royal Carribean | H56: Other | I56: Interview Scheduled | J56: Hardik | K56: 46107 | L56: 46107 | M56: 46111 | N56: EX LAVONNE AND CITYGUILDS | P56: =IFERROR(MasterData!$B56,"") -> Red turtle | Q56: =IFERROR(MasterData!$C56,"") -> Hostess | R56: =IFERROR(MasterData!$E56,"") | S56: =IFERROR(MasterData!$G56,"") | T56: =IFERROR(MasterData!$I56,"")
A57: PIP-054 | C57: Aaghaz AMir | D57: EDD | E57: CLI-054 | F57: Executive Chef | G57: STAGIER | H57: Mumbai | I57: Result Awaited | J57: Hardik | K57: 46107 | L57: 46110 | M57: 46110 | P57: =IFERROR(MasterData!$B57,"") -> Ritika & Co. | Q57: =IFERROR(MasterData!$C57,"") -> Junior Bartender | R57: =IFERROR(MasterData!$E57,"") | S57: =IFERROR(MasterData!$G57,"") | T57: =IFERROR(MasterData!$I57,"")
A58: PIP-055 | C58: Ram Singh | D58: All In | E58: CLI-055 | F58: F&B Controller | H58: Mumbai | I58: Rejected | J58: Aakash | K58: 46107 | L58: 46107 | M58: 46113 | O58: Didn't join | P58: =IFERROR(MasterData!$B58,"") -> Scarlett House | Q58: =IFERROR(MasterData!$C58,"") -> Junior Sous Chef | R58: =IFERROR(MasterData!$E58,"") | S58: =IFERROR(MasterData!$G58,"") | T58: =IFERROR(MasterData!$I58,"")
A59: PIP-056 | C59: Neha Sambherao | D59: Bastian | E59: CLI-056 | F59: Social Media Manager | G59: Things2do | H59: Mumbai | I59: Joined | J59: Aakash | K59: 46107 | L59: 46107 | M59: 46122 | P59: =IFERROR(MasterData!$B59,"") -> Shalimar | Q59: =IFERROR(MasterData!$C59,"") -> Kitchen Helper | R59: =IFERROR(MasterData!$E59,"") | S59: =IFERROR(MasterData!$G59,"") | T59: =IFERROR(MasterData!$I59,"")
A60: PIP-057 | C60: Raushun Kumar | D60: SLH | E60: CLI-057 | F60: Captain | G60: Seven Eleven | H60: Other | I60: Offer Accepted | J60: Hardik | K60: 46107 | L60: 46102 | M60: 46102 | N60: Selected joining on 10th April | P60: =IFERROR(MasterData!$B60,"") -> Shalimar Hotel | Q60: =IFERROR(MasterData!$C60,"") -> Kitchen Supervisor | R60: =IFERROR(MasterData!$E60,"") | S60: =IFERROR(MasterData!$G60,"") | T60: =IFERROR(MasterData!$I60,"")
A61: PIP-058 | C61: Ketan Shejwal | D61: Penang Table | E61: CLI-058 | F61: Bartender | G61: Jio | H61: Mumbai | I61: Hold | J61: Aakash | K61: 46107 | L61: 46146 | M61: 46150 | O61: Waiting for Candidate confirmation | P61: =IFERROR(MasterData!$B61,"") -> Silver Train | Q61: =IFERROR(MasterData!$C61,"") -> L&D | R61: =IFERROR(MasterData!$E61,"") | S61: =IFERROR(MasterData!$G61,"") | T61: =IFERROR(MasterData!$I61,"")
A62: PIP-059 | C62: Aryan Chaudhari | D62: Foodmatters | E62: CLI-059 | F62: Steward | G62: Mirage Hotel | H62: Mumbai | I62: Joined | J62: Hardik | K62: 46107 | L62: 46101 | M62: 46101 | P62: =IFERROR(MasterData!$B62,"") -> Sivako | Q62: =IFERROR(MasterData!$C62,"") -> Marketing Manager | R62: =IFERROR(MasterData!$E62,"") | S62: =IFERROR(MasterData!$G62,"") | T62: =IFERROR(MasterData!$I62,"")
A63: PIP-060 | C63: Prathamesh Keluskar | D63: True Palate | E63: CLI-060 | F63: General Manager | G63: Bayview | H63: Goa | I63: Sent to Client | J63: Edwin | K63: 46108 | P63: =IFERROR(MasterData!$B63,"") -> Slink and Bardot | Q63: =IFERROR(MasterData!$C63,"") -> Mixologist | R63: =IFERROR(MasterData!$E63,"") | S63: =IFERROR(MasterData!$G63,"") | T63: =IFERROR(MasterData!$I63,"")
A64: PIP-061 | C64: Umair Shaikh | D64: Blondie | E64: CLI-061 | F64: Commi 1 | G64: Compass | H64: Mumbai | I64: Selected | J64: Aakash | K64: 46108 | L64: 46112 | M64: 46113 | P64: =IFERROR(MasterData!$B64,"") -> Speciality | Q64: =IFERROR(MasterData!$C64,"") -> OTA | R64: =IFERROR(MasterData!$E64,"") | S64: =IFERROR(MasterData!$G64,"") | T64: =IFERROR(MasterData!$I64,"")
A65: PIP-062 | C65: Priyanshu Tripathi | D65: Speciality | E65: CLI-062 | F65: Captain | G65: None | H65: Other | I65: Joined | J65: Aakash | K65: 46108 | L65: 46119 | M65: 46119 | P65: =IFERROR(MasterData!$B65,"") -> Splendour | Q65: =IFERROR(MasterData!$C65,"") -> Operations Head | R65: =IFERROR(MasterData!$E65,"") | S65: =IFERROR(MasterData!$G65,"") | T65: =IFERROR(MasterData!$I65,"")
A66: PIP-063 | B66: =IF(C66="","","CAN-"&TEXT(66,"000")) -> CAN-066 | C66: Eesha Jhaveri | D66: Le 15 | E66: CLI-063 | F66: Commi 3 | G66: Burma Burma | H66: Mumbai | I66: Selected | J66: Aakash | K66: 46108 | L66: 46111 | M66: 46113 | P66: =IFERROR(MasterData!$B66,"") -> TAB | Q66: =IFERROR(MasterData!$C66,"") -> Operations Manager | R66: =IFERROR(MasterData!$E66,"") | S66: =IFERROR(MasterData!$G66,"") | T66: =IFERROR(MasterData!$I66,"")
A67: PIP-064 | C67: Royce Dsouza | D67: All in | E67: CLI-064 | F67: Steward | G67: None | H67: Mumbai | I67: Rejected | J67: Aakash | K67: 46108 | L67: 46114 | M67: 46115 | O67: Rejected offer, didn't join | P67: =IFERROR(MasterData!$B67,"") -> TAT | Q67: =IFERROR(MasterData!$C67,"") -> Other | R67: =IFERROR(MasterData!$E67,"") | S67: =IFERROR(MasterData!$G67,"") | T67: =IFERROR(MasterData!$I67,"")
A68: PIP-065 | B68: =IF(C68="","","CAN-"&TEXT(78,"000")) -> CAN-078 | C68: Senpong Chuba | D68: Circa 11 | E68: CLI-015 | F68: Bartender | G68: The Leela Palace, Bangalore | H68: Bangalore | I68: Interview Scheduled | J68: Edwin | K68: 46110 | P68: =IFERROR(MasterData!$B68,"") -> The Hummingtree | Q68: =IFERROR(MasterData!$C68,"") -> Outlet Manager | R68: =IFERROR(MasterData!$E68,"") | S68: =IFERROR(MasterData!$G68,"") | T68: =IFERROR(MasterData!$I68,"")
A69: PIP-066 | B69: =IF(C69="","","CAN-"&TEXT(79,"000")) -> CAN-079 | C69: Ruthvik | D69: Circa 11 | E69: CLI-015 | F69: Senior Captain | G69: Postcard Hotel | H69: Bangalore | I69: Sent to Client | J69: Edwin | K69: 46110 | P69: =IFERROR(MasterData!$B69,"") -> The Kin Hotel | Q69: =IFERROR(MasterData!$C69,"") -> Outlet Supervisor | R69: =IFERROR(MasterData!$E69,"") | S69: =IFERROR(MasterData!$G69,"") | T69: =IFERROR(MasterData!$I69,"")
A70: PIP-067 | B70: =IF(C70="","","CAN-"&TEXT(80,"000")) -> CAN-080 | C70: Ridhik Khati | D70: Circa 11 | E70: CLI-015 | F70: Captain | G70: Mulki | H70: Bangalore | I70: Sent to Client | J70: Edwin | K70: 46110 | P70: =IFERROR(MasterData!$B70,"") -> The Nest | Q70: =IFERROR(MasterData!$C70,"") -> PR | R70: =IFERROR(MasterData!$E70,"") | S70: =IFERROR(MasterData!$G70,"") | T70: =IFERROR(MasterData!$I70,"")
A71: PIP-068 | B71: =IF(C71="","","CAN-"&TEXT(81,"000")) -> CAN-081 | C71: Om Salgaonkar | D71: ABNAH | E71: CLI-038 | F71: Commi 1 | G71: Slink&Bardot | H71: Mumbai | I71: Offer Accepted | J71: Edwin | K71: 46110 | P71: =IFERROR(MasterData!$B71,"") -> The Ranch | Q71: =IFERROR(MasterData!$C71,"") -> PR Executive | R71: =IFERROR(MasterData!$E71,"") | S71: =IFERROR(MasterData!$G71,"") | T71: =IFERROR(MasterData!$I71,"")
A72: PIP-069 | B72: =IF(C72="","","CAN-"&TEXT(82,"000")) -> CAN-082 | C72: Ashlesha Vinde | D72: Hunger Inc | E72: CLI-031 | F72: Captain | G72: Hylo Taproom | H72: Mumbai | I72: Sent to Client | J72: Edwin | K72: 46110 | P72: =IFERROR(MasterData!$B72,"") -> Tropicool | Q72: =IFERROR(MasterData!$C72,"") -> Packaging Assistant | R72: =IFERROR(MasterData!$E72,"") | S72: =IFERROR(MasterData!$G72,"") | T72: =IFERROR(MasterData!$I72,"")
A73: PIP-070 | B73: =IF(C73="","","CAN-"&TEXT(83,"000")) -> CAN-083 | C73: Ronak Shetty | D73: SLH | E73: CLI-077 | F73: Bar Manager | G73: Fushi Island | H73: Goa | I73: Interview Scheduled | J73: Hardik | K73: 46111 | L73: 46111 | M73: 46111 | P73: =IFERROR(MasterData!$B73,"") -> True palate | Q73: =IFERROR(MasterData!$C73,"") -> Payroll | R73: =IFERROR(MasterData!$E73,"") | S73: =IFERROR(MasterData!$G73,"") | T73: =IFERROR(MasterData!$I73,"")
A74: PIP-071 | B74: =IF(C74="","","CAN-"&TEXT(84,"000")) -> CAN-084 | C74: Shijin | D74: SLH | E74: CLI-077 | F74: Bartender | G74: EBS GOA | H74: Goa | I74: Result Awaited | J74: Hardik | K74: 46111 | L74: 46111 | M74: 46111 | P74: =IFERROR(MasterData!$B74,"") -> UGIPL | Q74: =IFERROR(MasterData!$C74,"") -> Purchase | R74: =IFERROR(MasterData!$E74,"") | S74: =IFERROR(MasterData!$G74,"") | T74: =IFERROR(MasterData!$I74,"")
A75: PIP-072 | B75: CAN-086 | C75: Rakesh Kumar | D75: SLH | E75: CLI-077 | F75: Senior Sous Chef | G75: DLF HOSPITALITY | H75: Delhi | I75: Interview Scheduled | J75: Hardik | K75: 46111 | L75: 46111 | M75: 46111 | P75: =IFERROR(MasterData!$B75,"") -> Zima | Q75: =IFERROR(MasterData!$C75,"") -> QC | R75: =IFERROR(MasterData!$E75,"") | S75: =IFERROR(MasterData!$G75,"") | T75: =IFERROR(MasterData!$I75,"")
A76: PIP-073 | B76: =IF(C76="","","CAN-"&TEXT(89,"000")) -> CAN-089 | C76: Ninoshka Satam | D76: All in | F76: HR | G76: None | H76: Mumbai | I76: Hold | J76: Aakash | K76: 46111 | L76: 46120 | M76: 46121 | O76: Telphonic round done, scheduled for f2f | P76: =IFERROR(MasterData!$B76,"") -> HNH Salad | Q76: =IFERROR(MasterData!$C76,"") -> RM | R76: =IFERROR(MasterData!$E76,"") | S76: =IFERROR(MasterData!$G76,"") | T76: =IFERROR(MasterData!$I76,"")
A77: PIP-074 | B77: =IF(C77="","","CAN-"&TEXT(91,"000")) -> CAN-091 | C77: Sahil Shaikh | D77: Bastian | F77: HR | G77: Hinduja | H77: Mumbai | I77: Rejected | J77: Aakash | K77: 46111 | L77: 46119 | M77: 46120 | O77: Candidate joined elsewhere | P77: =IFERROR(MasterData!$B77,"") -> Apero by Malvika | Q77: =IFERROR(MasterData!$C77,"") -> Receptionist | R77: =IFERROR(MasterData!$E77,"") | S77: =IFERROR(MasterData!$G77,"") | T77: =IFERROR(MasterData!$I77,"")
C78: Madhura Thanekar | D78: Le 15 | F78: Commi 1 | G78: None | H78: Mumbai | I78: Rejected | J78: Mohit | K78: 46111 | P78: =IFERROR(MasterData!$B78,"") -> Bastian | Q78: =IFERROR(MasterData!$C78,"") -> Room Sales | R78: =IFERROR(MasterData!$E78,"") | S78: =IFERROR(MasterData!$G78,"") | T78: =IFERROR(MasterData!$I78,"")
C79: Vaishali Maurya | D79: Blondie | F79: GRE | G79: None | H79: Mumbai | I79: Candidate Dropped | J79: Mohit | K79: 46132 | P79: =IFERROR(MasterData!$B79,"") -> Green Gains | Q79: =IFERROR(MasterData!$C79,"") -> SCM Head | R79: =IFERROR(MasterData!$E79,"") | S79: =IFERROR(MasterData!$G79,"") | T79: =IFERROR(MasterData!$I79,"")
C80: Karan Chauhan | D80: Blondie | F80: Senior Barista | G80: None | H80: Mumbai | I80: Candidate Dropped | J80: Mohit | K80: 46111 | P80: =IFERROR(MasterData!$B80,"") -> SLH | Q80: =IFERROR(MasterData!$C80,"") -> Sales | R80: =IFERROR(MasterData!$E80,"") | S80: =IFERROR(MasterData!$G80,"") | T80: =IFERROR(MasterData!$I80,"")
C81: Devesh Katkar | D81: Le 15 | F81: Outlet Manager | G81: None | H81: Mumbai | I81: Interview Scheduled | J81: Mohit | K81: 46111 | P81: =IFERROR(MasterData!$B81,"") -> Niko | Q81: =IFERROR(MasterData!$C81,"") -> Senior Barista | R81: =IFERROR(MasterData!$E81,"") | S81: =IFERROR(MasterData!$G81,"") | T81: =IFERROR(MasterData!$I81,"")
C82: Rushabh Jadhav | D82: Hunger Inc | F82: Supervisor | G82: Raheja | H82: Mumbai | I82: Rejected | J82: Mohit | K82: 46111 | P82: =IFERROR(MasterData!$B82,"") -> Courtside | Q82: =IFERROR(MasterData!$C82,"") -> Senior Bartender | R82: =IFERROR(MasterData!$E82,"") | S82: =IFERROR(MasterData!$G82,"") | T82: =IFERROR(MasterData!$I82,"")
C83: Kunal Salian | D83: All in | F83: Bartender | G83: None | H83: Mumbai | I83: Candidate Dropped | J83: Aakash | K83: 46112 | L83: 46114 | M83: 46114 | O83: DNR | P83: =IFERROR(MasterData!$B83,"") -> Penang Table | Q83: =IFERROR(MasterData!$C83,"") -> Senior CDP | R83: =IFERROR(MasterData!$E83,"") | S83: =IFERROR(MasterData!$G83,"") | T83: =IFERROR(MasterData!$I83,"")
B84: =IF(C84="","","CAN-"&TEXT(100,"000")) -> CAN-100 | C84: Rohan Hajare | D84: All in | F84: Captain | G84: Fresh catch | H84: Mumbai | I84: Candidate Dropped | J84: Aakash | K84: 46112 | L84: 46114 | M84: 46113 | O84: DNR | P84: =IFERROR(MasterData!$B85,"") -> Corleone's | Q84: =IFERROR(MasterData!$C85,"") -> Senior GRE | R84: =IFERROR(MasterData!$E85,"") | S84: =IFERROR(MasterData!$G85,"") | T84: =IFERROR(MasterData!$I85,"")
C85: Aniket Parulekar | D85: ABNAH | F85: Sous Chef | G85: Bastian | H85: Mumbai | I85: Rejected | J85: Aakash | K85: 46112 | L85: 46112 | M85: 46113 | O85: Didn't fit in budget | P85: =IFERROR(MasterData!$B86,"") -> Nenapu | Q85: =IFERROR(MasterData!$C86,"") -> Senior Sous Chef | R85: =IFERROR(MasterData!$E86,"") | S85: =IFERROR(MasterData!$G86,"") | T85: =IFERROR(MasterData!$I86,"")
C86: Harsh Kadam | D86: Blondie | F86: F&B Associate | G86: None | H86: Mumbai | I86: Rejected | J86: Mohit | K86: 46112 | P86: =IFERROR(MasterData!$B87,"") | Q86: =IFERROR(MasterData!$C87,"") -> Senior Steward | R86: =IFERROR(MasterData!$E87,"") | S86: =IFERROR(MasterData!$G87,"") | T86: =IFERROR(MasterData!$I87,"")
C87: Sayyad Sagir | D87: Blondie | F87: Senior Captain | G87: None | H87: Mumbai | I87: Interview Scheduled | J87: Mohit | K87: 46112 | P87: =IFERROR(MasterData!$B88,"") | Q87: =IFERROR(MasterData!$C88,"") -> Social Media Manager | R87: =IFERROR(MasterData!$E88,"") | S87: =IFERROR(MasterData!$G88,"") | T87: =IFERROR(MasterData!$I88,"")
C88: Lakshita Shaw | D88: Blondie | F88: Steward | G88: Love & Latte | H88: Mumbai | I88: Joined | J88: Aakash | K88: 46113 | L88: 46114 | M88: 46115 | P88: =IFERROR(MasterData!$B89,"") | Q88: =IFERROR(MasterData!$C89,"") -> Sommelier | R88: =IFERROR(MasterData!$E89,"") | S88: =IFERROR(MasterData!$G89,"") | T88: =IFERROR(MasterData!$I89,"")
C89: Lanmi Zingkhai | D89: Blondie | F89: Steward | G89: None | H89: Mumbai | I89: Candidate Dropped | J89: Aakash | K89: 46113 | L89: 46113 | M89: 46114 | P89: =IFERROR(MasterData!$B90,"") | Q89: =IFERROR(MasterData!$C90,"") -> Sous Chef | R89: =IFERROR(MasterData!$E90,"") | S89: =IFERROR(MasterData!$G90,"") | T89: =IFERROR(MasterData!$I90,"")
C90: Khanimphi Khudai | D90: Blondie | F90: Hostess | G90: The Indus club | H90: Mumbai | I90: Candidate Dropped | J90: Aakash | K90: 46113 | L90: 46113 | M90: 46114 | P90: =IFERROR(MasterData!$B91,"") | Q90: =IFERROR(MasterData!$C91,"") -> Sr. Duty Manager | R90: =IFERROR(MasterData!$E91,"") | S90: =IFERROR(MasterData!$G91,"") | T90: =IFERROR(MasterData!$I91,"")
C91: Rajeev Kashyap | D91: Green Gains | F91: Kitchen Helper | G91: none | H91: Mumbai | I91: Hold | J91: Aakash | K91: 46114 | L91: 46114 | M91: 46114 | P91: =IFERROR(MasterData!$B92,"") | Q91: =IFERROR(MasterData!$C92,"") -> Steward | R91: =IFERROR(MasterData!$E92,"") | S91: =IFERROR(MasterData!$G92,"") | T91: =IFERROR(MasterData!$I92,"")
C92: Nitin Panwaar | D92: ABNAH | F92: Commi 2 | G92: None | H92: Mumbai | I92: Candidate Dropped | J92: Aakash | K92: 46114 | L92: 46119 | M92: 46115 | P92: =IFERROR(MasterData!$B93,"") | Q92: =IFERROR(MasterData!$C93,"") -> Store Manager | R92: =IFERROR(MasterData!$E93,"") | S92: =IFERROR(MasterData!$G93,"") | T92: =IFERROR(MasterData!$I93,"")
C93: Sanket Adawade | D93: ABNAH | F93: Commi 2 | G93: Dave & Busters | H93: Mumbai | I93: Candidate Dropped | J93: Aakash | K93: 46114 | L93: 46115 | M93: 46117 | P93: =IFERROR(MasterData!$B94,"") | Q93: =IFERROR(MasterData!$C94,"") -> Stores Manager | R93: =IFERROR(MasterData!$E94,"") | S93: =IFERROR(MasterData!$G94,"") | T93: =IFERROR(MasterData!$I94,"")
C94: Sagar Warekar | D94: ABNAH | F94: Commi 1 | G94: Dave & Busters | H94: Mumbai | I94: Candidate Dropped | J94: Aakash | K94: 46114 | L94: 46114 | M94: 46117 | P94: =IFERROR(MasterData!$B95,"") | Q94: =IFERROR(MasterData!$C95,"") -> Supervisor | R94: =IFERROR(MasterData!$E95,"") | S94: =IFERROR(MasterData!$G95,"") | T94: =IFERROR(MasterData!$I95,"")
C95: Faiz Khan | D95: All in | F95: Captain | G95: None | H95: Mumbai | I95: Candidate Dropped | J95: Aakash | K95: 46114 | L95: 46119 | M95: 46119 | P95: =IFERROR(MasterData!$B96,"") | Q95: =IFERROR(MasterData!$C96,"") -> Supply Chain | R95: =IFERROR(MasterData!$E96,"") | S95: =IFERROR(MasterData!$G96,"") | T95: =IFERROR(MasterData!$I96,"")
C96: Sneha Salgaonkar | D96: ABNAH | F96: GRE | G96: None | H96: Mumbai | I96: Result Awaited | J96: Mohit | K96: 46115 | P96: =IFERROR(MasterData!$B97,"") | Q96: =IFERROR(MasterData!$C97,"") -> Team Leader | R96: =IFERROR(MasterData!$E97,"") | S96: =IFERROR(MasterData!$G97,"") | T96: =IFERROR(MasterData!$I97,"")
C97: Asif Kalnad | D97: Blondie | F97: Executive Chef | G97: Bare | H97: Mumbai | I97: Rejected | J97: Mohit | K97: 46114 | P97: =IFERROR(MasterData!$B98,"") | Q97: =IFERROR(MasterData!$C98,"") -> Trainee Captain | R97: =IFERROR(MasterData!$E98,"") | S97: =IFERROR(MasterData!$G98,"") | T97: =IFERROR(MasterData!$I98,"")
C98: Leon Dsouza | D98: Blondie | F98: Executive Chef | G98: None | H98: Mumbai | I98: Rejected | J98: Mohit | K98: 46114 | P98: =IFERROR(MasterData!$B99,"") | Q98: =IFERROR(MasterData!$C99,"") -> Training Manager | R98: =IFERROR(MasterData!$E99,"") | S98: =IFERROR(MasterData!$G99,"") | T98: =IFERROR(MasterData!$I99,"")
C99: Prajwal Sawant | D99: Donmai | F99: Commi 2 | G99: None | H99: Mumbai | I99: Candidate Dropped | J99: Mohit | K99: 46114 | P99: =IFERROR(MasterData!$B100,"") | Q99: =IFERROR(MasterData!$C100,"") -> Waiter | R99: =IFERROR(MasterData!$E100,"") | S99: =IFERROR(MasterData!$G100,"") | T99: =IFERROR(MasterData!$I100,"")
C100: Sunil Makwana | D100: Blondie | F100: Steward | G100: None | H100: Mumbai | I100: Candidate Dropped | J100: Mohit | K100: 03-Ape-26 | P100: =IFERROR(MasterData!$B101,"") | Q100: =IFERROR(MasterData!$C101,"") -> Aggregator Manager | R100: =IFERROR(MasterData!$E101,"") | S100: =IFERROR(MasterData!$G101,"") | T100: =IFERROR(MasterData!$I101,"")
...

Sheet Dashboard
A1: 📊 RECRUITMENT DASHBOARD — Auto-updates. No manual entry needed here.
A3: LIVE OVERVIEW
A4: Open Positions | B4: Total Seats Open | C4: Seats Filled | D4: Total In Pipeline | E4: Sent to Client | F4: Offers Accepted | G4: Candidate Dropped | H4: Joined
A5: =COUNTIF('Open Positions'!K:K,"Open") -> 101 | B5: =SUMIF('Open Positions'!K:K,"Open",'Open Positions'!J:J) -> 383 | C5: =SUMIF('Open Positions'!K:K,"Open",'Open Positions'!N:N) -> 5 | D5: =COUNTA('Candidate Pipeline'!C4:C998)-COUNTIF('Candidate Pipeline'!I4:I998,"Joined")-COUNTIF('Candidate Pipeline'!I4:I998,"Candidate Dropped") -> 202 | E5: =COUNTIF('Candidate Pipeline'!I:I,"Sent to Client") -> 34 | F5: =COUNTIF('Candidate Pipeline'!I:I,"Offer Accepted") -> 11 | G5: =COUNTIF('Candidate Pipeline'!I:I,"Candidate Dropped") -> 65 | H5: =COUNTIF('Candidate Pipeline'!I:I,"Joined") -> 13
A7: PIPELINE STAGE BREAKDOWN | E7: RECRUITER STATS
A8: Stage | B8: Count | C8: % of Pipeline | E8: Recruiter | F8: Open Seats | G8: In Pipeline | H8: Joined
A9: Sent to Client | B9: =COUNTIF('Candidate Pipeline'!I:I,"Sent to Client") -> 34 | C9: =IFERROR(COUNTIF('Candidate Pipeline'!I:I,"Sent to Client")/COUNTA('Candidate Pipeline'!C4:C998),0) -> 0.12142857 | E9: Edwin | F9: =SUMIFS('Open Positions'!J:J,'Open Positions'!I:I,"Edwin",'Open Positions'!K:K,"Open") -> 62 | G9: =COUNTIFS('Candidate Pipeline'!J:J,"Edwin",'Candidate Pipeline'!I:I,"<>Joined",'Candidate Pipeline'!I:I,"<>Candidate Dropped") -> 16 | H9: =COUNTIFS('Candidate Pipeline'!J:J,"Edwin",'Candidate Pipeline'!I:I,"Joined") -> 1
A10: Interview Scheduled | B10: =COUNTIF('Candidate Pipeline'!I:I,"Interview Scheduled") -> 88 | C10: =IFERROR(COUNTIF('Candidate Pipeline'!I:I,"Interview Scheduled")/COUNTA('Candidate Pipeline'!C4:C998),0) -> 0.31428571 | E10: Manokamna | F10: =SUMIFS('Open Positions'!J:J,'Open Positions'!I:I,"Manokamna",'Open Positions'!K:K,"Open") -> 54 | G10: =COUNTIFS('Candidate Pipeline'!J:J,"Manokamna",'Candidate Pipeline'!I:I,"<>Joined",'Candidate Pipeline'!I:I,"<>Candidate Dropped") -> 2 | H10: =COUNTIFS('Candidate Pipeline'!J:J,"Manokamna",'Candidate Pipeline'!I:I,"Joined") -> 0
A11: Result Awaited | B11: =COUNTIF('Candidate Pipeline'!I:I,"Result Awaited") -> 9 | C11: =IFERROR(COUNTIF('Candidate Pipeline'!I:I,"Result Awaited")/COUNTA('Candidate Pipeline'!C4:C998),0) -> 0.032142857 | E11: Hardik | F11: =SUMIFS('Open Positions'!J:J,'Open Positions'!I:I,"Hardik",'Open Positions'!K:K,"Open") -> 17 | G11: =COUNTIFS('Candidate Pipeline'!J:J,"Hardik",'Candidate Pipeline'!I:I,"<>Joined",'Candidate Pipeline'!I:I,"<>Candidate Dropped") -> 30 | H11: =COUNTIFS('Candidate Pipeline'!J:J,"Hardik",'Candidate Pipeline'!I:I,"Joined") -> 2
A12: Selected | B12: =COUNTIF('Candidate Pipeline'!I:I,"Selected") -> 20 | C12: =IFERROR(COUNTIF('Candidate Pipeline'!I:I,"Selected")/COUNTA('Candidate Pipeline'!C4:C998),0) -> 0.071428571 | E12: Mohit | F12: =SUMIFS('Open Positions'!J:J,'Open Positions'!I:I,"Mohit",'Open Positions'!K:K,"Open") -> 177 | G12: =COUNTIFS('Candidate Pipeline'!J:J,"Mohit",'Candidate Pipeline'!I:I,"<>Joined",'Candidate Pipeline'!I:I,"<>Candidate Dropped") -> 63 | H12: =COUNTIFS('Candidate Pipeline'!J:J,"Mohit",'Candidate Pipeline'!I:I,"Joined") -> 4
A13: Rejected | B13: =COUNTIF('Candidate Pipeline'!I:I,"Rejected") -> 34 | C13: =IFERROR(COUNTIF('Candidate Pipeline'!I:I,"Rejected")/COUNTA('Candidate Pipeline'!C4:C998),0) -> 0.12142857 | E13: Aakash | F13: =SUMIFS('Open Positions'!J:J,'Open Positions'!I:I,"Aakash",'Open Positions'!K:K,"Open") -> 73 | G13: =COUNTIFS('Candidate Pipeline'!J:J,"Aakash",'Candidate Pipeline'!I:I,"<>Joined",'Candidate Pipeline'!I:I,"<>Candidate Dropped") -> 91 | H13: =COUNTIFS('Candidate Pipeline'!J:J,"Aakash",'Candidate Pipeline'!I:I,"Joined") -> 6
A14: Hold | B14: =COUNTIF('Candidate Pipeline'!I:I,"Hold") -> 7 | C14: =IFERROR(COUNTIF('Candidate Pipeline'!I:I,"Hold")/COUNTA('Candidate Pipeline'!C4:C998),0) -> 0.025
A15: Offer Sent | B15: =COUNTIF('Candidate Pipeline'!I:I,"Offer Sent") -> 0 | C15: =IFERROR(COUNTIF('Candidate Pipeline'!I:I,"Offer Sent")/COUNTA('Candidate Pipeline'!C4:C998),0) -> 0
A16: Offer Accepted | B16: =COUNTIF('Candidate Pipeline'!I:I,"Offer Accepted") -> 11 | C16: =IFERROR(COUNTIF('Candidate Pipeline'!I:I,"Offer Accepted")/COUNTA('Candidate Pipeline'!C4:C998),0) -> 0.039285714
A17: Joined | B17: =COUNTIF('Candidate Pipeline'!I:I,"Joined") -> 13 | C17: =IFERROR(COUNTIF('Candidate Pipeline'!I:I,"Joined")/COUNTA('Candidate Pipeline'!C4:C998),0) -> 0.046428571
A18: Candidate Dropped | B18: =COUNTIF('Candidate Pipeline'!I:I,"Candidate Dropped") -> 65 | C18: =IFERROR(COUNTIF('Candidate Pipeline'!I:I,"Candidate Dropped")/COUNTA('Candidate Pipeline'!C4:C998),0) -> 0.23214286
A20: CLIENT ACTIVITY — updates automatically
A21: Every client added to Open Positions appears here automatically.
A22: Client Name | B22: Client ID | C22: Open Positions | D22: Total Seats | E22: Filled | F22: Remaining | G22: In Pipeline | H22: Joined
A23: ABNAH | B23: {=IF(A23="","",IFERROR(INDEX(MasterData!$A$4:$A$500,MATCH(A23,MasterData!$B$4:$B$500,0)),""))} -> CLI-001 | C23: =IF(A23="","",COUNTIFS('Open Positions'!B:B,A23,'Open Positions'!K:K,"Open")) -> 13 | D23: =IF(A23="","",SUMIFS('Open Positions'!J:J,'Open Positions'!B:B,A23,'Open Positions'!K:K,"Open")) -> 54 | E23: =IF(A23="","",SUMIFS('Open Positions'!N:N,'Open Positions'!B:B,A23,'Open Positions'!K:K,"Open")) -> 0 | F23: =IF(A23="","",SUMIFS('Open Positions'!O:O,'Open Positions'!B:B,A23,'Open Positions'!K:K,"Open")) -> 16 | G23: =IF(A23="","",COUNTIFS('Candidate Pipeline'!D:D,A23,'Candidate Pipeline'!I:I,"<>Joined",'Candidate Pipeline'!I:I,"<>Candidate Dropped")) -> 29 | H23: =IF(A23="","",COUNTIFS('Candidate Pipeline'!D:D,A23,'Candidate Pipeline'!I:I,"Joined")) -> 1
A24: Abhinav Immigration | B24: {=IF(A24="","",IFERROR(INDEX(MasterData!$A$4:$A$500,MATCH(A24,MasterData!$B$4:$B$500,0)),""))} -> CLI-002 | C24: =IF(A24="","",COUNTIFS('Open Positions'!B:B,A24,'Open Positions'!K:K,"Open")) -> 0 | D24: =IF(A24="","",SUMIFS('Open Positions'!J:J,'Open Positions'!B:B,A24,'Open Positions'!K:K,"Open")) -> 0 | E24: =IF(A24="","",SUMIFS('Open Positions'!N:N,'Open Positions'!B:B,A24,'Open Positions'!K:K,"Open")) -> 0 | F24: =IF(A24="","",SUMIFS('Open Positions'!O:O,'Open Positions'!B:B,A24,'Open Positions'!K:K,"Open")) -> 0 | G24: =IF(A24="","",COUNTIFS('Candidate Pipeline'!D:D,A24,'Candidate Pipeline'!I:I,"<>Joined",'Candidate Pipeline'!I:I,"<>Candidate Dropped")) -> 0 | H24: =IF(A24="","",COUNTIFS('Candidate Pipeline'!D:D,A24,'Candidate Pipeline'!I:I,"Joined")) -> 0
A25: Adarsh Sweets | B25: {=IF(A25="","",IFERROR(INDEX(MasterData!$A$4:$A$500,MATCH(A25,MasterData!$B$4:$B$500,0)),""))} -> CLI-003 | C25: =IF(A25="","",COUNTIFS('Open Positions'!B:B,A25,'Open Positions'!K:K,"Open")) -> 0 | D25: =IF(A25="","",SUMIFS('Open Positions'!J:J,'Open Positions'!B:B,A25,'Open Positions'!K:K,"Open")) -> 0 | E25: =IF(A25="","",SUMIFS('Open Positions'!N:N,'Open Positions'!B:B,A25,'Open Positions'!K:K,"Open")) -> 0 | F25: =IF(A25="","",SUMIFS('Open Positions'!O:O,'Open Positions'!B:B,A25,'Open Positions'!K:K,"Open")) -> 0 | G25: =IF(A25="","",COUNTIFS('Candidate Pipeline'!D:D,A25,'Candidate Pipeline'!I:I,"<>Joined",'Candidate Pipeline'!I:I,"<>Candidate Dropped")) -> 0 | H25: =IF(A25="","",COUNTIFS('Candidate Pipeline'!D:D,A25,'Candidate Pipeline'!I:I,"Joined")) -> 0
A26: Agarwal Biryani | B26: {=IF(A26="","",IFERROR(INDEX(MasterData!$A$4:$A$500,MATCH(A26,MasterData!$B$4:$B$500,0)),""))} -> CLI-004 | C26: =IF(A26="","",COUNTIFS('Open Positions'!B:B,A26,'Open Positions'!K:K,"Open")) -> 0 | D26: =IF(A26="","",SUMIFS('Open Positions'!J:J,'Open Positions'!B:B,A26,'Open Positions'!K:K,"Open")) -> 0 | E26: =IF(A26="","",SUMIFS('Open Positions'!N:N,'Open Positions'!B:B,A26,'Open Positions'!K:K,"Open")) -> 0 | F26: =IF(A26="","",SUMIFS('Open Positions'!O:O,'Open Positions'!B:B,A26,'Open Positions'!K:K,"Open")) -> 0 | G26: =IF(A26="","",COUNTIFS('Candidate Pipeline'!D:D,A26,'Candidate Pipeline'!I:I,"<>Joined",'Candidate Pipeline'!I:I,"<>Candidate Dropped")) -> 0 | H26: =IF(A26="","",COUNTIFS('Candidate Pipeline'!D:D,A26,'Candidate Pipeline'!I:I,"Joined")) -> 0
A27: All in | B27: {=IF(A27="","",IFERROR(INDEX(MasterData!$A$4:$A$500,MATCH(A27,MasterData!$B$4:$B$500,0)),""))} -> CLI-005 | C27: =IF(A27="","",COUNTIFS('Open Positions'!B:B,A27,'Open Positions'!K:K,"Open")) -> 7 | D27: =IF(A27="","",SUMIFS('Open Positions'!J:J,'Open Positions'!B:B,A27,'Open Positions'!K:K,"Open")) -> 19 | E27: =IF(A27="","",SUMIFS('Open Positions'!N:N,'Open Positions'!B:B,A27,'Open Positions'!K:K,"Open")) -> 0 | F27: =IF(A27="","",SUMIFS('Open Positions'!O:O,'Open Positions'!B:B,A27,'Open Positions'!K:K,"Open")) -> 18 | G27: =IF(A27="","",COUNTIFS('Candidate Pipeline'!D:D,A27,'Candidate Pipeline'!I:I,"<>Joined",'Candidate Pipeline'!I:I,"<>Candidate Dropped")) -> 14 | H27: =IF(A27="","",COUNTIFS('Candidate Pipeline'!D:D,A27,'Candidate Pipeline'!I:I,"Joined")) -> 1
A28: Aria Communication | B28: {=IF(A28="","",IFERROR(INDEX(MasterData!$A$4:$A$500,MATCH(A28,MasterData!$B$4:$B$500,0)),""))} -> CLI-006 | C28: =IF(A28="","",COUNTIFS('Open Positions'!B:B,A28,'Open Positions'!K:K,"Open")) -> 0 | D28: =IF(A28="","",SUMIFS('Open Positions'!J:J,'Open Positions'!B:B,A28,'Open Positions'!K:K,"Open")) -> 0 | E28: =IF(A28="","",SUMIFS('Open Positions'!N:N,'Open Positions'!B:B,A28,'Open Positions'!K:K,"Open")) -> 0 | F28: =IF(A28="","",SUMIFS('Open Positions'!O:O,'Open Positions'!B:B,A28,'Open Positions'!K:K,"Open")) -> 0 | G28: =IF(A28="","",COUNTIFS('Candidate Pipeline'!D:D,A28,'Candidate Pipeline'!I:I,"<>Joined",'Candidate Pipeline'!I:I,"<>Candidate Dropped")) -> 0 | H28: =IF(A28="","",COUNTIFS('Candidate Pipeline'!D:D,A28,'Candidate Pipeline'!I:I,"Joined")) -> 0
A29: Atmosphere | B29: {=IF(A29="","",IFERROR(INDEX(MasterData!$A$4:$A$500,MATCH(A29,MasterData!$B$4:$B$500,0)),""))} -> CLI-007 | C29: =IF(A29="","",COUNTIFS('Open Positions'!B:B,A29,'Open Positions'!K:K,"Open")) -> 0 | D29: =IF(A29="","",SUMIFS('Open Positions'!J:J,'Open Positions'!B:B,A29,'Open Positions'!K:K,"Open")) -> 0 | E29: =IF(A29="","",SUMIFS('Open Positions'!N:N,'Open Positions'!B:B,A29,'Open Positions'!K:K,"Open")) -> 0 | F29: =IF(A29="","",SUMIFS('Open Positions'!O:O,'Open Positions'!B:B,A29,'Open Positions'!K:K,"Open")) -> 0 | G29: =IF(A29="","",COUNTIFS('Candidate Pipeline'!D:D,A29,'Candidate Pipeline'!I:I,"<>Joined",'Candidate Pipeline'!I:I,"<>Candidate Dropped")) -> 0 | H29: =IF(A29="","",COUNTIFS('Candidate Pipeline'!D:D,A29,'Candidate Pipeline'!I:I,"Joined")) -> 0
A30: August Café | B30: {=IF(A30="","",IFERROR(INDEX(MasterData!$A$4:$A$500,MATCH(A30,MasterData!$B$4:$B$500,0)),""))} -> CLI-008 | C30: =IF(A30="","",COUNTIFS('Open Positions'!B:B,A30,'Open Positions'!K:K,"Open")) -> 0 | D30: =IF(A30="","",SUMIFS('Open Positions'!J:J,'Open Positions'!B:B,A30,'Open Positions'!K:K,"Open")) -> 0 | E30: =IF(A30="","",SUMIFS('Open Positions'!N:N,'Open Positions'!B:B,A30,'Open Positions'!K:K,"Open")) -> 0 | F30: =IF(A30="","",SUMIFS('Open Positions'!O:O,'Open Positions'!B:B,A30,'Open Positions'!K:K,"Open")) -> 0 | G30: =IF(A30="","",COUNTIFS('Candidate Pipeline'!D:D,A30,'Candidate Pipeline'!I:I,"<>Joined",'Candidate Pipeline'!I:I,"<>Candidate Dropped")) -> 0 | H30: =IF(A30="","",COUNTIFS('Candidate Pipeline'!D:D,A30,'Candidate Pipeline'!I:I,"Joined")) -> 0
A31: Aures hospitality | B31: {=IF(A31="","",IFERROR(INDEX(MasterData!$A$4:$A$500,MATCH(A31,MasterData!$B$4:$B$500,0)),""))} -> CLI-009 | C31: =IF(A31="","",COUNTIFS('Open Positions'!B:B,A31,'Open Positions'!K:K,"Open")) -> 0 | D31: =IF(A31="","",SUMIFS('Open Positions'!J:J,'Open Positions'!B:B,A31,'Open Positions'!K:K,"Open")) -> 0 | E31: =IF(A31="","",SUMIFS('Open Positions'!N:N,'Open Positions'!B:B,A31,'Open Positions'!K:K,"Open")) -> 0 | F31: =IF(A31="","",SUMIFS('Open Positions'!O:O,'Open Positions'!B:B,A31,'Open Positions'!K:K,"Open")) -> 0 | G31: =IF(A31="","",COUNTIFS('Candidate Pipeline'!D:D,A31,'Candidate Pipeline'!I:I,"<>Joined",'Candidate Pipeline'!I:I,"<>Candidate Dropped")) -> 0 | H31: =IF(A31="","",COUNTIFS('Candidate Pipeline'!D:D,A31,'Candidate Pipeline'!I:I,"Joined")) -> 0
A32: BB | B32: {=IF(A32="","",IFERROR(INDEX(MasterData!$A$4:$A$500,MATCH(A32,MasterData!$B$4:$B$500,0)),""))} -> CLI-010 | C32: =IF(A32="","",COUNTIFS('Open Positions'!B:B,A32,'Open Positions'!K:K,"Open")) -> 0 | D32: =IF(A32="","",SUMIFS('Open Positions'!J:J,'Open Positions'!B:B,A32,'Open Positions'!K:K,"Open")) -> 0 | E32: =IF(A32="","",SUMIFS('Open Positions'!N:N,'Open Positions'!B:B,A32,'Open Positions'!K:K,"Open")) -> 0 | F32: =IF(A32="","",SUMIFS('Open Positions'!O:O,'Open Positions'!B:B,A32,'Open Positions'!K:K,"Open")) -> 0 | G32: =IF(A32="","",COUNTIFS('Candidate Pipeline'!D:D,A32,'Candidate Pipeline'!I:I,"<>Joined",'Candidate Pipeline'!I:I,"<>Candidate Dropped")) -> 0 | H32: =IF(A32="","",COUNTIFS('Candidate Pipeline'!D:D,A32,'Candidate Pipeline'!I:I,"Joined")) -> 0
A33: BTC | B33: {=IF(A33="","",IFERROR(INDEX(MasterData!$A$4:$A$500,MATCH(A33,MasterData!$B$4:$B$500,0)),""))} -> CLI-011 | C33: =IF(A33="","",COUNTIFS('Open Positions'!B:B,A33,'Open Positions'!K:K,"Open")) -> 0 | D33: =IF(A33="","",SUMIFS('Open Positions'!J:J,'Open Positions'!B:B,A33,'Open Positions'!K:K,"Open")) -> 0 | E33: =IF(A33="","",SUMIFS('Open Positions'!N:N,'Open Positions'!B:B,A33,'Open Positions'!K:K,"Open")) -> 0 | F33: =IF(A33="","",SUMIFS('Open Positions'!O:O,'Open Positions'!B:B,A33,'Open Positions'!K:K,"Open")) -> 0 | G33: =IF(A33="","",COUNTIFS('Candidate Pipeline'!D:D,A33,'Candidate Pipeline'!I:I,"<>Joined",'Candidate Pipeline'!I:I,"<>Candidate Dropped")) -> 0 | H33: =IF(A33="","",COUNTIFS('Candidate Pipeline'!D:D,A33,'Candidate Pipeline'!I:I,"Joined")) -> 0
A34: Baesic Fit | B34: {=IF(A34="","",IFERROR(INDEX(MasterData!$A$4:$A$500,MATCH(A34,MasterData!$B$4:$B$500,0)),""))} -> CLI-012 | C34: =IF(A34="","",COUNTIFS('Open Positions'!B:B,A34,'Open Positions'!K:K,"Open")) -> 0 | D34: =IF(A34="","",SUMIFS('Open Positions'!J:J,'Open Positions'!B:B,A34,'Open Positions'!K:K,"Open")) -> 0 | E34: =IF(A34="","",SUMIFS('Open Positions'!N:N,'Open Positions'!B:B,A34,'Open Positions'!K:K,"Open")) -> 0 | F34: =IF(A34="","",SUMIFS('Open Positions'!O:O,'Open Positions'!B:B,A34,'Open Positions'!K:K,"Open")) -> 0 | G34: =IF(A34="","",COUNTIFS('Candidate Pipeline'!D:D,A34,'Candidate Pipeline'!I:I,"<>Joined",'Candidate Pipeline'!I:I,"<>Candidate Dropped")) -> 0 | H34: =IF(A34="","",COUNTIFS('Candidate Pipeline'!D:D,A34,'Candidate Pipeline'!I:I,"Joined")) -> 0
... A94: Zima | B94: {=IF(A94="","",IFERROR(INDEX(MasterData!$A$4:$A$500,MATCH(A94,MasterData!$B$4:$B$500,0)),""))} -> CLI-072 | C94: =IF(A94="","",COUNTIFS('Open Positions'!B:B,A94,'Open Positions'!K:K,"Open")) -> 0 | D94: =IF(A94="","",SUMIFS('Open Positions'!J:J,'Open Positions'!B:B,A94,'Open Positions'!K:K,"Open")) -> 0 | E94: =IF(A94="","",SUMIFS('Open Positions'!N:N,'Open Positions'!B:B,A94,'Open Positions'!K:K,"Open")) -> 0 | F94: =IF(A94="","",SUMIFS('Open Positions'!O:O,'Open Positions'!B:B,A94,'Open Positions'!K:K,"Open")) -> 0 | G94: =IF(A94="","",COUNTIFS('Candidate Pipeline'!D:D,A94,'Candidate Pipeline'!I:I,"<>Joined",'Candidate Pipeline'!I:I,"<>Candidate Dropped")) -> 0 | H94: =IF(A94="","",COUNTIFS('Candidate Pipeline'!D:D,A94,'Candidate Pipeline'!I:I,"Joined")) -> 0
